{
  "projects": [
    {
      "projectName": "Central-West Orana REZ Transmission",
      "location": "Central-West Orana, NSW",
      "country": "Australia",
      "procurementStart": "H1 2025",
      "procurementStatus": "Under Construction",
      "assetTypes": [
        "HV Transmission",
        "REZ",
        "Substation"
      ],
      "owner": "EnergyCo NSW",
      "epcContractor": "Acciona, UGL, GE Vernova, Consolidated Power Projects (CPP)",
      "financiers": [
        "NSW Government"
      ],
      "projectValue": "AUD 3.5 billion",
      "capacityMW": 0,
      "mpEngagementWindow": "Immediate – HV sub/transm equipment FAT/QAQC ongoing.",
      "mpServices": [
        "QAQC Inspection",
        "Factory Acceptance Testing",
        "Site Supervision"
      ],
      "priority": "High",
      "sourceUrl": "energyco.nsw.gov.au",
      "summary": "Develop 330kV/500kV transm lines/subs for REZs. Involves HV transformers, breakers, switchgear.",
      "statusNote": "Construction active. Key packages awarded. EnergyCo NSW Q2 2025.",
      "statusConfidence": "high"
    },
    {
      "projectName": "Hunter-Central Coast REZ Transmission",
      "location": "Hunter-Central Coast, NSW",
      "country": "Australia",
      "procurementStart": "Q3 2026",
      "procurementStatus": "Planning",
      "assetTypes": [
        "HV Transmission",
        "REZ",
        "Substation"
      ],
      "owner": "EnergyCo NSW",
      "epcContractor": "",
      "financiers": [
        "NSW Government"
      ],
      "projectValue": "AUD 2.0 billion (estimated)",
      "capacityMW": 0,
      "mpEngagementWindow": "Engage H2 2025 – HV asset procurement strategy defined.",
      "mpServices": [
        "Technical Due Diligence",
        "QAQC Inspection"
      ],
      "priority": "Medium",
      "sourceUrl": "energyco.nsw.gov.au",
      "summary": "Planning new 500kV/330kV transm lines/subs for REZ. Significant HV equipment expected.",
      "statusNote": "Development/assessment active. EnergyCo NSW Q2 2025.",
      "statusConfidence": "high"
    },
    {
      "projectName": "New England REZ Transmission",
      "location": "New England, NSW",
      "country": "Australia",
      "procurementStart": "Q4 2026",
      "procurementStatus": "Planning",
      "assetTypes": [
        "HV Transmission",
        "REZ",
        "Substation"
      ],
      "owner": "EnergyCo NSW",
      "epcContractor": "",
      "financiers": [
        "NSW Government"
      ],
      "projectValue": "AUD 1.8 billion (estimated)",
      "capacityMW": 0,
      "mpEngagementWindow": "Engage H1 2026 – approvals underway, EPC tender late 2026.",
      "mpServices": [
        "Technical Due Diligence",
        "QAQC Inspection"
      ],
      "priority": "Medium",
      "sourceUrl": "energyco.nsw.gov.au",
      "summary": "Early planning for critical transm infrastructure/subs to unlock REZ. New HV transformers/switchgear.",
      "statusNote": "Project agreement signed. EnergyCo NSW Q2 2025.",
      "statusConfidence": "high"
    },
    {
      "projectName": "Marinus Link (Stage 1)",
      "location": "Tasmania to Victoria",
      "country": "Australia",
      "procurementStart": "Q1 2024",
      "procurementStatus": "Under Construction",
      "assetTypes": [
        "HV Transmission",
        "Substation"
      ],
      "owner": "Marinus Link Pty Ltd",
      "epcContractor": "Hitachi Energy (HVDC converter stations), Prysmian Group (cables)",
      "financiers": [
        "Australian Government",
        "Tasmanian Government",
        "Victorian Government"
      ],
      "projectValue": "AUD 3.5 billion",
      "capacityMW": 0,
      "mpEngagementWindow": "Immediate – HVDC converter station equipment FAT/QAQC needed.",
      "mpServices": [
        "Factory Acceptance Testing",
        "QAQC Inspection",
        "Site Supervision"
      ],
      "priority": "High",
      "sourceUrl": "marinuslink.com.au",
      "summary": "Stage 1 of 750MW HVDC interconnector. Involves complex HVDC transformers, converters, switchgear.",
      "statusNote": "FID late 2023, early works active. Marinus Link Q2 2025.",
      "statusConfidence": "high"
    },
    {
      "projectName": "Project EnergyConnect (NSW-SA Interconnector)",
      "location": "Robertstown (SA) to Wagga Wagga (NSW)",
      "country": "Australia",
      "procurementStart": "Q3 2024",
      "procurementStatus": "Under Construction",
      "assetTypes": [
        "HV Transmission",
        "Substation"
      ],
      "owner": "Transgrid (NSW), ElectraNet (SA)",
      "epcContractor": "Acciona (SA), SecureEnergy (Downer/Elecnor/Omexom JV) (NSW)",
      "financiers": [
        "Transgrid",
        "ElectraNet"
      ],
      "projectValue": "AUD 2.4 billion",
      "capacityMW": 0,
      "mpEngagementWindow": "Engage now – ongoing HV equipment inspections for substation components.",
      "mpServices": [
        "QAQC Inspection",
        "Factory Acceptance Testing",
        "Site Supervision"
      ],
      "priority": "High",
      "sourceUrl": "transgrid.com.au",
      "summary": "New 330kV interconnector. Major HV transformers, circuit breakers, and switchgear key components.",
      "statusNote": "Construction advanced, completion mid-2026. Transgrid Q2 2025.",
      "statusConfidence": "high"
    },
    {
      "projectName": "Goyder Renewables Zone (Stage 1)",
      "location": "Goyder, SA",
      "country": "Australia",
      "procurementStart": "Q1 2025",
      "procurementStatus": "Under Construction",
      "assetTypes": [
        "Wind",
        "BESS",
        "Substation"
      ],
      "owner": "Neoen",
      "epcContractor": "GE (wind turbines), PCL Construction (balance of plant)",
      "financiers": [
        "CEFC",
        "Clean Energy Finance Corporation",
        "BNP Paribas",
        "NAB",
        "Westpac"
      ],
      "projectValue": "AUD 1.4 billion",
      "capacityMW": 562,
      "mpEngagementWindow": "Engage now – ongoing FAT/QAQC for BESS and wind components.",
      "mpServices": [
        "QAQC Inspection",
        "Factory Acceptance Testing",
        "Site Supervision"
      ],
      "priority": "High",
      "sourceUrl": "neoen.com",
      "summary": "Stage 1: 412MW wind + 150MW/300MWh BESS. Significant HV equipment for battery/grid.",
      "statusNote": "Construction ongoing for wind/BESS. Neoen Q2 2025.",
      "statusConfidence": "high"
    },
    {
      "projectName": "MacIntyre Wind Farm and BESS",
      "location": "MacIntyre, QLD",
      "country": "Australia",
      "procurementStart": "Q2 2025",
      "procurementStatus": "Under Construction",
      "assetTypes": [
        "Wind",
        "BESS",
        "Substation"
      ],
      "owner": "CleanCo Queensland, Ark Energy",
      "epcContractor": "ACCIONA Energía",
      "financiers": [
        "CleanCo",
        "Ark Energy"
      ],
      "projectValue": "AUD 2.0 billion",
      "capacityMW": 1126,
      "mpEngagementWindow": "Immediate – specialist FAT/QAQC for sub/BESS open.",
      "mpServices": [
        "QAQC Inspection",
        "Factory Acceptance Testing",
        "Site Supervision"
      ],
      "priority": "High",
      "sourceUrl": "macintyrewindfarm.com.au",
      "summary": "1026MW wind farm + 100MW BESS. New 330kV substation, significant grid connection. Key HV.",
      "statusNote": "Construction active for wind/sub, BESS progressing. MacIntyre Q2 2025.",
      "statusConfidence": "high"
    },
    {
      "projectName": "Western Downs Green Power Hub - BESS",
      "location": "Western Downs, QLD",
      "country": "Australia",
      "procurementStart": "Q3 2024",
      "procurementStatus": "Under Construction",
      "assetTypes": [
        "BESS",
        "Substation"
      ],
      "owner": "RWE Renewables",
      "epcContractor": "TBD (BESS)",
      "financiers": [],
      "projectValue": "AUD 150 million (BESS portion)",
      "capacityMW": 100,
      "mpEngagementWindow": "Engage now – BESS FAT/QAQC opportunities for 2025.",
      "mpServices": [
        "QAQC Inspection",
        "Factory Acceptance Testing",
        "Site Supervision"
      ],
      "priority": "High",
      "sourceUrl": "rwe.com",
      "summary": "100MW/200MWh BESS addition to 400MW solar. New HV connections/substation upgrades.",
      "statusNote": "BESS announced 2024, construction commenced. RWE Renewables Q2 2025.",
      "statusConfidence": "high"
    },
    {
      "projectName": "Bulli Creek Solar Farm",
      "location": "Bulli Creek, QLD",
      "country": "Australia",
      "procurementStart": "Q4 2026",
      "procurementStatus": "Planning",
      "assetTypes": [
        "Solar PV",
        "BESS",
        "Substation",
        "HV Transmission"
      ],
      "owner": "Energy Estate, UPC/AC Renewables Australia",
      "epcContractor": "",
      "financiers": [],
      "projectValue": "AUD 2.0 billion+",
      "capacityMW": 1400,
      "mpEngagementWindow": "Engage H2 2025 – early engagement for future sub/BESS procurement.",
      "mpServices": [
        "Technical Due Diligence",
        "QAQC Inspection"
      ],
      "priority": "Medium",
      "sourceUrl": "energyestate.com",
      "summary": "~1GW solar farm + 400MW BESS. Requires extensive grid connection, new 330kV substation.",
      "statusNote": "Environmental approvals progressing. Energy Estate Q2 2025.",
      "statusConfidence": "high"
    },
    {
      "projectName": "Waipapa Wind Farm",
      "location": "Central Queensland, QLD",
      "country": "Australia",
      "procurementStart": "Q1 2025",
      "procurementStatus": "Under Construction",
      "assetTypes": [
        "Wind",
        "Substation"
      ],
      "owner": "Tilt Renewables",
      "epcContractor": "Vestas (wind turbines)",
      "financiers": [
        "ANZ",
        "Westpac",
        "Sumitomo Mitsui Banking Corp",
        "Bank of China"
      ],
      "projectValue": "AUD 450 million",
      "capacityMW": 200,
      "mpEngagementWindow": "Engage now – ongoing FAT/QAQC for BoP and substation.",
      "mpServices": [
        "QAQC Inspection",
        "Factory Acceptance Testing",
        "Site Supervision"
      ],
      "priority": "High",
      "sourceUrl": "tiltrenewables.com",
      "summary": "200MW wind farm connecting to 275kV line with substation upgrades. Involves HV circuit breakers.",
      "statusNote": "Construction active with turbines being installed. Tilt Renewables Q2 2025.",
      "statusConfidence": "high"
    },
    {
      "projectName": "NextDC S3 Sydney Supernode",
      "location": "Artarmon, Sydney, NSW",
      "country": "Australia",
      "procurementStart": "Q2 2025",
      "procurementStatus": "Under Construction",
      "assetTypes": [
        "Data Centre",
        "Substation",
        "HV Transmission"
      ],
      "owner": "NextDC",
      "epcContractor": "Kapitol Group",
      "financiers": [],
      "projectValue": "AUD 1.5 billion+",
      "capacityMW": 120,
      "mpEngagementWindow": "Immediate – HV infrastructure/substation equipment QAQC for build.",
      "mpServices": [
        "QAQC Inspection",
        "Factory Acceptance Testing",
        "Site Supervision"
      ],
      "priority": "High",
      "sourceUrl": "nextdc.com",
      "summary": "Hyperscale data centre, HV substations, continuous HV transformer procurement for power needs.",
      "statusNote": "Construction ongoing with phased development. NextDC Q2 2025.",
      "statusConfidence": "high"
    },
    {
      "projectName": "AirTrunk SYD3",
      "location": "Western Sydney, NSW",
      "country": "Australia",
      "procurementStart": "Q3 2025",
      "procurementStatus": "Under Construction",
      "assetTypes": [
        "Data Centre",
        "Substation",
        "HV Transmission"
      ],
      "owner": "AirTrunk",
      "epcContractor": "",
      "financiers": [],
      "projectValue": "AUD 1.0 billion+",
      "capacityMW": 100,
      "mpEngagementWindow": "Engage now – ongoing HV equipment procurement for power infrastructure.",
      "mpServices": [
        "QAQC Inspection",
        "Factory Acceptance Testing",
        "Site Supervision"
      ],
      "priority": "High",
      "sourceUrl": "airtrunk.com",
      "summary": "Hyperscale data centre expansion. Robust HV grid connections, dedicated substations. Focus HV transformers.",
      "statusNote": "Phased construction underway, capacity expansion 2024. AirTrunk Q2 2025.",
      "statusConfidence": "high"
    },
    {
      "projectName": "Microsoft Data Centre Expansion (NSW)",
      "location": "Sydney Metropolitan Area, NSW",
      "country": "Australia",
      "procurementStart": "Q2 2025",
      "procurementStatus": "Under Construction",
      "assetTypes": [
        "Data Centre",
        "Substation"
      ],
      "owner": "Microsoft",
      "epcContractor": "",
      "financiers": [],
      "projectValue": "AUD 500 million+",
      "capacityMW": 0,
      "mpEngagementWindow": "Engage now – continuous procurement of HV transformers, switchgear.",
      "mpServices": [
        "QAQC Inspection",
        "Factory Acceptance Testing",
        "Site Supervision"
      ],
      "priority": "High",
      "sourceUrl": "planningportal.nsw.gov.au",
      "summary": "Phased expansion of Microsoft data centre. New substations, HV grid connections for power.",
      "statusNote": "Multiple DAs and construction phases 2024-2025. NSW Planning Portal Q2 2025.",
      "statusConfidence": "high"
    },
    {
      "projectName": "Gold Coast Data Centre",
      "location": "Gold Coast, QLD",
      "country": "Australia",
      "procurementStart": "Q1 2027",
      "procurementStatus": "Planning",
      "assetTypes": [
        "Data Centre",
        "Substation"
      ],
      "owner": "TBD (Hyperscale Developer)",
      "epcContractor": "",
      "financiers": [],
      "projectValue": "AUD 300 million+",
      "capacityMW": 0,
      "mpEngagementWindow": "Engage H2 2026 – major sub design/procurement planning post-FID.",
      "mpServices": [
        "Technical Due Diligence",
        "QAQC Inspection"
      ],
      "priority": "Low",
      "sourceUrl": "utilitymagazine.com.au",
      "summary": "Proposed hyperscale data centre. New 275kV substation, significant HV infrastructure scope.",
      "statusNote": "New 275kV substation requirement reported 2024. Utility Magazine Q2 2025.",
      "statusConfidence": "medium"
    },
    {
      "projectName": "Narrabri Energy Hub (Solar + BESS)",
      "location": "Narrabri, NSW",
      "country": "Australia",
      "procurementStart": "H1 2026",
      "procurementStatus": "Planning",
      "assetTypes": [
        "Solar PV",
        "BESS",
        "Substation",
        "REZ"
      ],
      "owner": "Lightsource bp",
      "epcContractor": "",
      "financiers": [],
      "projectValue": "AUD 700 million",
      "capacityMW": 500,
      "mpEngagementWindow": "Engage H2 2025 – pre-tender EPC, HV equipment packages.",
      "mpServices": [
        "Technical Due Diligence",
        "QAQC Inspection"
      ],
      "priority": "Medium",
      "sourceUrl": "lightsourcebp.com",
      "summary": "Proposed 500MW solar + 400MWh BESS in REZ. New substation, HV equipment needed.",
      "statusNote": "Environmental approval 2023, grid studies underway. Lightsource bp Q2 2025.",
      "statusConfidence": "high"
    },
    {
      "projectName": "Warragamba Dam Floating Solar",
      "location": "Warragamba Dam, NSW",
      "country": "Australia",
      "procurementStart": "Q1 2027",
      "procurementStatus": "Planning",
      "assetTypes": [
        "Solar PV",
        "Substation"
      ],
      "owner": "Sydney Water",
      "epcContractor": "",
      "financiers": [
        "NSW Government"
      ],
      "projectValue": "AUD 80 million",
      "capacityMW": 24,
      "mpEngagementWindow": "Engage H1 2026 – detailed design/procurement for substation.",
      "mpServices": [
        "Technical Due Diligence",
        "QAQC Inspection"
      ],
      "priority": "Low",
      "sourceUrl": "sydneywater.com.au",
      "summary": "Proposed 24MW floating solar. New/upgraded substation for grid, involving HV equipment.",
      "statusNote": "EIS exhibited 2024. Sydney Water Q2 2025.",
      "statusConfidence": "high"
    },
    {
      "projectName": "New England Solar Farm (Stage 2 & BESS)",
      "location": "New England, NSW",
      "country": "Australia",
      "procurementStart": "Q4 2024",
      "procurementStatus": "Under Construction",
      "assetTypes": [
        "Solar PV",
        "BESS",
        "Substation"
      ],
      "owner": "ACEN Australia",
      "epcContractor": "PCL Construction (Stage 1), TBD (BESS/Stage 2)",
      "financiers": [
        "CEFC"
      ],
      "projectValue": "AUD 1.0 billion+",
      "capacityMW": 720,
      "mpEngagementWindow": "Engage now – specialist QAQC for BESS and BoP Stage 2.",
      "mpServices": [
        "QAQC Inspection",
        "Factory Acceptance Testing",
        "Site Supervision"
      ],
      "priority": "High",
      "sourceUrl": "acenrenewables.com.au",
      "summary": "Second stage of 720MW solar farm and planned BESS addition. Significant HV substation/grid.",
      "statusNote": "Stage 1 operational, Stage 2 construction active. ACEN Australia Q2 2025.",
      "statusConfidence": "high"
    },
    {
      "projectName": "Moorabool Wind Farm Expansion",
      "location": "Moorabool, VIC",
      "country": "Australia",
      "procurementStart": "Q1 2025",
      "procurementStatus": "Under Construction",
      "assetTypes": [
        "Wind",
        "Substation"
      ],
      "owner": "Goldwind Australia",
      "epcContractor": "Goldwind (turbines)",
      "financiers": [],
      "projectValue": "AUD 700 million",
      "capacityMW": 312,
      "mpEngagementWindow": "Engage now – ongoing inspection of substation/grid upgrades.",
      "mpServices": [
        "QAQC Inspection",
        "Factory Acceptance Testing",
        "Site Supervision"
      ],
      "priority": "High",
      "sourceUrl": "mooraboolwindfarm.com",
      "summary": "Stage 2 Moorabool Wind Farm. Upgrades to local substations/grid, including HV transformers.",
      "statusNote": "Stage 1 operational, Stage 2 active, nearing completion. Goldwind Q2 2025.",
      "statusConfidence": "high"
    },
    {
      "projectName": "Limondale Solar Farm - BESS",
      "location": "Balranald, NSW",
      "country": "Australia",
      "procurementStart": "Q2 2024",
      "procurementStatus": "Under Construction",
      "assetTypes": [
        "BESS",
        "Substation"
      ],
      "owner": "RWE Renewables",
      "epcContractor": "GenusPlus (BESS balance of plant)",
      "financiers": [
        "CEFC",
        "NAB"
      ],
      "projectValue": "AUD 150 million",
      "capacityMW": 100,
      "mpEngagementWindow": "Immediate – BESS FAT/QAQC ongoing for 2025 commissioning.",
      "mpServices": [
        "QAQC Inspection",
        "Factory Acceptance Testing",
        "Site Supervision"
      ],
      "priority": "High",
      "sourceUrl": "rwe.com",
      "summary": "100MW/200MWh BESS to Limondale Solar. New HV connections/substation interface equipment.",
      "statusNote": "BESS announced/UC 2024 for 2025 operation. RWE Renewables Q2 2025.",
      "statusConfidence": "high"
    },
    {
      "projectName": "Kaban Green Power Hub",
      "location": "Far North Queensland, QLD",
      "country": "Australia",
      "procurementStart": "Q4 2024",
      "procurementStatus": "Under Construction",
      "assetTypes": [
        "Wind",
        "BESS",
        "Substation"
      ],
      "owner": "Neoen",
      "epcContractor": "Vestas (turbines), UGL (balance of plant)",
      "financiers": [
        "CEFC",
        "ANZ",
        "Clean Energy Finance Corporation"
      ],
      "projectValue": "AUD 600 million",
      "capacityMW": 257,
      "mpEngagementWindow": "Engage now – specialist FAT/QAQC for BESS/substation equipment.",
      "mpServices": [
        "QAQC Inspection",
        "Factory Acceptance Testing",
        "Site Supervision"
      ],
      "priority": "High",
      "sourceUrl": "neoen.com",
      "summary": "157MW wind + 100MW/100MWh BESS. New 132kV/275kV substation, HV transformers/switchgear.",
      "statusNote": "Construction ongoing, expected completion H1 2025. Neoen Q2 2025.",
      "statusConfidence": "high"
    },
    {
      "projectName": "Dinawan Energy Hub",
      "location": "Wagga Wagga, NSW",
      "country": "Australia",
      "procurementStart": "Q3 2026",
      "procurementStatus": "Planning",
      "assetTypes": [
        "Solar PV",
        "BESS",
        "Substation"
      ],
      "owner": "Energy Estate",
      "epcContractor": "",
      "financiers": [],
      "projectValue": "AUD 800 million+",
      "capacityMW": 800,
      "mpEngagementWindow": "Engage H2 2025 – early positioning for future EPC/HV equipment.",
      "mpServices": [
        "Technical Due Diligence",
        "QAQC Inspection"
      ],
      "priority": "Medium",
      "sourceUrl": "energyestate.com",
      "summary": "Proposed ~400MW solar + 400MW BESS. Significant substation/HV grid infrastructure needed.",
      "statusNote": "Environmental approval 2023, grid studies underway. Energy Estate Q2 2025.",
      "statusConfidence": "high"
    },
    {
      "projectName": "Star of the South Offshore Wind",
      "location": "Gippsland Coast, VIC",
      "country": "Australia",
      "procurementStart": "Q1 2028",
      "procurementStatus": "Planning",
      "assetTypes": [
        "Wind",
        "HV Transmission",
        "Substation"
      ],
      "owner": "Star of the South (Copenhagen Infrastructure Partners, Cbus Super)",
      "epcContractor": "",
      "financiers": [],
      "projectValue": "AUD 10 billion+",
      "capacityMW": 2200,
      "mpEngagementWindow": "Engage H1 2026 – early for subsea cables, offshore/onshore subs.",
      "mpServices": [
        "Technical Due Diligence",
        "QAQC Inspection"
      ],
      "priority": "Low",
      "sourceUrl": "starofthesouth.com.au",
      "summary": "Australia's first offshore wind (2.2GW). Extensive HV transmission, offshore/onshore substations. Massive.",
      "statusNote": "Feasibility license 2024, environmental approvals progressing. Star of the South Q2 2025.",
      "statusConfidence": "high"
    },
    {
      "projectName": "Transgrid VNI West / KerangLink",
      "location": "Western Victoria to Western NSW",
      "country": "Australia",
      "procurementStart": "Q3 2027",
      "procurementStatus": "Planning",
      "assetTypes": [
        "HV Transmission",
        "Substation"
      ],
      "owner": "Transgrid, AEMO",
      "epcContractor": "",
      "financiers": [
        "Australian Government"
      ],
      "projectValue": "AUD 3.3 billion",
      "capacityMW": 0,
      "mpEngagementWindow": "Engage H1 2026 – major project, long lead HV equipment.",
      "mpServices": [
        "Technical Due Diligence",
        "QAQC Inspection"
      ],
      "priority": "Medium",
      "sourceUrl": "transgrid.com.au",
      "summary": "New 500kV interconnector, NSW-VIC. Critical for energy security, large HV equipment involved.",
      "statusNote": "RIT-T 2023, route/environmental assessment active. Transgrid Q2 2025.",
      "statusConfidence": "high"
    },
    {
      "projectName": "Kiamal Solar Farm - BESS Extension",
      "location": "Kiamal, VIC",
      "country": "Australia",
      "procurementStart": "Q2 2024",
      "procurementStatus": "Under Construction",
      "assetTypes": [
        "BESS",
        "Substation"
      ],
      "owner": "Total Eren",
      "epcContractor": "",
      "financiers": [],
      "projectValue": "AUD 150 million",
      "capacityMW": 100,
      "mpEngagementWindow": "Immediate – BESS and associated substation equipment FAT/QAQC.",
      "mpServices": [
        "QAQC Inspection",
        "Factory Acceptance Testing",
        "Site Supervision"
      ],
      "priority": "High",
      "sourceUrl": "total-eren.com",
      "summary": "100MW/200MWh BESS to Kiamal Solar. Integration existing substation, new HV equipment.",
      "statusNote": "BESS project announced 2023, construction active. Total Eren Q2 2025.",
      "statusConfidence": "high"
    },
    {
      "projectName": "Neoen Collie Battery",
      "location": "Collie, WA",
      "country": "Australia",
      "procurementStart": "Q1 2024",
      "procurementStatus": "Under Construction",
      "assetTypes": [
        "BESS",
        "Substation"
      ],
      "owner": "Neoen",
      "epcContractor": "UGL (balance of plant), Fluence (BESS technology)",
      "financiers": [
        "CEFC"
      ],
      "projectValue": "AUD 300 million",
      "capacityMW": 219,
      "mpEngagementWindow": "Immediate – FAT/QAQC for BESS units and substation equipment.",
      "mpServices": [
        "QAQC Inspection",
        "Factory Acceptance Testing",
        "Site Supervision"
      ],
      "priority": "High",
      "sourceUrl": "neoen.com",
      "summary": "219MW / 877MWh BESS connected to existing Collie substation. Significant HV equipment for grid.",
      "statusNote": "Construction active, expected completion H1 2025. Neoen Q2 2025.",
      "statusConfidence": "high"
    },
    {
      "projectName": "X-Elio Blue Grass Solar Farm",
      "location": "Queensland",
      "country": "Australia",
      "procurementStart": "Q2 2025",
      "procurementStatus": "Under Construction",
      "assetTypes": [
        "Solar PV",
        "BESS",
        "Substation"
      ],
      "owner": "X-Elio",
      "epcContractor": "Gransolar (GRS)",
      "financiers": [
        "BNP Paribas",
        "Clean Energy Finance Corporation (CEFC)",
        "Santander",
        "SMBC"
      ],
      "projectValue": "AUD 450 million",
      "capacityMW": 300,
      "mpEngagementWindow": "Engage now – specialist FAT/QAQC for BESS and sub equipment.",
      "mpServices": [
        "QAQC Inspection",
        "Factory Acceptance Testing",
        "Site Supervision"
      ],
      "priority": "High",
      "sourceUrl": "x-elio.com",
      "summary": "200MW solar + 100MW/200MWh BESS. Includes new substation and grid connection, involving HV equipment.",
      "statusNote": "Construction active, expected completion H1 2025. X-Elio Q2 2025.",
      "statusConfidence": "high"
    },
    {
      "projectName": "Ark Energy Chinchilla Battery",
      "location": "Chinchilla, QLD",
      "country": "Australia",
      "procurementStart": "Q1 2024",
      "procurementStatus": "Under Construction",
      "assetTypes": [
        "BESS",
        "Substation"
      ],
      "owner": "Ark Energy (Korea Zinc subsidiary)",
      "epcContractor": "UGL (balance of plant), Fluence (BESS technology)",
      "financiers": [],
      "projectValue": "AUD 250 million",
      "capacityMW": 100,
      "mpEngagementWindow": "Immediate – FAT and QAQC for BESS units and associated substation.",
      "mpServices": [
        "QAQC Inspection",
        "Factory Acceptance Testing",
        "Site Supervision"
      ],
      "priority": "High",
      "sourceUrl": "arkenergy.com.au",
      "summary": "100MW / 200MWh BESS project connecting to existing grid. Requires new HV connections.",
      "statusNote": "Construction commenced for H2 2025 operation. Ark Energy Q2 2025.",
      "statusConfidence": "high"
    },
    {
      "projectName": "Kidston Pumped Hydro and Solar",
      "location": "Kidston, QLD",
      "country": "Australia",
      "procurementStart": "Q3 2024",
      "procurementStatus": "Under Construction",
      "assetTypes": [
        "Hydro",
        "Solar PV",
        "Substation"
      ],
      "owner": "Genex Power",
      "epcContractor": "McConnell Dowell / John Holland JV",
      "financiers": [
        "NAIF",
        "ARENA",
        "CEFC"
      ],
      "projectValue": "AUD 1.4 billion",
      "capacityMW": 300,
      "mpEngagementWindow": "Engage now – final FAT for major electrical/hydro equipment.",
      "mpServices": [
        "QAQC Inspection",
        "Factory Acceptance Testing",
        "Site Supervision"
      ],
      "priority": "High",
      "sourceUrl": "genexpower.com.au",
      "summary": "250MW pumped hydro storage with 50MW solar. Significant HV electrical plant, substation infrastructure.",
      "statusNote": "Construction substantially complete, commissioning H1 2025. Genex Power Q2 2025.",
      "statusConfidence": "high"
    },
    {
      "projectName": "Waratah Super Battery",
      "location": "Lake Munmorah, NSW",
      "country": "Australia",
      "procurementStart": "Q1 2025",
      "procurementStatus": "Under Construction",
      "assetTypes": [
        "BESS",
        "Substation",
        "HV Transmission"
      ],
      "owner": "Akari Power (BlackRock)",
      "epcContractor": "Tesla (Megapacks), Transgrid (connection infrastructure)",
      "financiers": [
        "NSW Government"
      ],
      "projectValue": "AUD 1.0 billion",
      "capacityMW": 700,
      "mpEngagementWindow": "Immediate – ongoing QAQC/FAT for large BESS and grid equipment.",
      "mpServices": [
        "QAQC Inspection",
        "Factory Acceptance Testing",
        "Site Supervision"
      ],
      "priority": "High",
      "sourceUrl": "energyco.nsw.gov.au",
      "summary": "700MW / 1400MWh BESS, 'virtual transmission'. Extensive HV connections, complex grid.",
      "statusNote": "Construction active, rapid progress for mid-2025. EnergyCo NSW Q2 2025.",
      "statusConfidence": "high"
    },
    {
      "projectName": "Lotus Creek Wind Farm",
      "location": "Lotus Creek, QLD",
      "country": "Australia",
      "procurementStart": "Q2 2027",
      "procurementStatus": "Planning",
      "assetTypes": [
        "Wind",
        "Substation"
      ],
      "owner": "RES Australia",
      "epcContractor": "",
      "financiers": [],
      "projectValue": "AUD 800 million",
      "capacityMW": 400,
      "mpEngagementWindow": "Engage H1 2026 – early for EPC tender/substation equipment.",
      "mpServices": [
        "Technical Due Diligence",
        "QAQC Inspection"
      ],
      "priority": "Low",
      "sourceUrl": "res-group.com",
      "summary": "Proposed 400MW wind farm. New substation/transmission line to grid. Involves HV transformers.",
      "statusNote": "Environmental approval 2023, grid studies progressing. RES Australia Q2 2025.",
      "statusConfidence": "high"
    },
    {
      "projectName": "Bowmans Creek Battery",
      "location": "Muswellbrook, NSW",
      "country": "Australia",
      "procurementStart": "Q2 2025",
      "procurementStatus": "Under Construction",
      "assetTypes": [
        "BESS",
        "Substation"
      ],
      "owner": "AGL Energy",
      "epcContractor": "Wärtsilä",
      "financiers": [],
      "projectValue": "AUD 400 million",
      "capacityMW": 500,
      "mpEngagementWindow": "Immediate – FAT/QAQC for BESS units/grid connection equipment.",
      "mpServices": [
        "QAQC Inspection",
        "Factory Acceptance Testing",
        "Site Supervision"
      ],
      "priority": "High",
      "sourceUrl": "agl.com.au",
      "summary": "500MW / 1000MWh BESS project co-located. Significant HV transformers and switchgear.",
      "statusNote": "FID Q4 2023, construction active, mid-2026. AGL Q2 2025.",
      "statusConfidence": "high"
    },
    {
      "projectName": "Liddell BESS",
      "location": "Muswellbrook, NSW",
      "country": "Australia",
      "procurementStart": "Q2 2025",
      "procurementStatus": "Under Construction",
      "assetTypes": [
        "BESS",
        "Substation"
      ],
      "owner": "AGL Energy",
      "epcContractor": "Valmec",
      "financiers": [],
      "projectValue": "AUD 400 million",
      "capacityMW": 500,
      "mpEngagementWindow": "Immediate – FAT/QAQC for BESS units/grid connection equipment.",
      "mpServices": [
        "QAQC Inspection",
        "Factory Acceptance Testing",
        "Site Supervision"
      ],
      "priority": "High",
      "sourceUrl": "agl.com.au",
      "summary": "500MW / 1000MWh BESS at Liddell. Existing HV grid but requires new transformers.",
      "statusNote": "FID Q4 2023, construction active, mid-2026. AGL Q2 2025.",
      "statusConfidence": "high"
    },
    {
      "projectName": "Silverleaf Solar Farm",
      "location": "Western Downs, QLD",
      "country": "Australia",
      "procurementStart": "Q4 2026",
      "procurementStatus": "Planning",
      "assetTypes": [
        "Solar PV",
        "BESS",
        "Substation"
      ],
      "owner": "RES Australia",
      "epcContractor": "",
      "financiers": [],
      "projectValue": "AUD 500 million",
      "capacityMW": 250,
      "mpEngagementWindow": "Engage H2 2025 – early engagement for future EPC/HV equipment.",
      "mpServices": [
        "Technical Due Diligence",
        "QAQC Inspection"
      ],
      "priority": "Medium",
      "sourceUrl": "res-group.com",
      "summary": "Proposed ~250MW solar farm + potential BESS, new substation/grid connection. HV equipment.",
      "statusNote": "Environmental approval 2023, grid studies underway. RES Australia Q2 2025.",
      "statusConfidence": "high"
    },
    {
      "projectName": "Uralla Solar Farm",
      "location": "Uralla, NSW",
      "country": "Australia",
      "procurementStart": "H1 2027",
      "procurementStatus": "Planning",
      "assetTypes": [
        "Solar PV",
        "BESS",
        "Substation"
      ],
      "owner": "UPC/AC Renewables Australia",
      "epcContractor": "",
      "financiers": [],
      "projectValue": "AUD 600 million",
      "capacityMW": 400,
      "mpEngagementWindow": "Engage H2 2026 – monitor for environmental approvals/EPC tender.",
      "mpServices": [
        "Technical Due Diligence",
        "QAQC Inspection"
      ],
      "priority": "Low",
      "sourceUrl": "upc-acrenewables.com",
      "summary": "Proposed 400MW solar farm + BESS in REZ. New substation/grid connection. HV equipment.",
      "statusNote": "EIS submission/assessment ongoing 2024. UPC/AC Renewables Q2 2025.",
      "statusConfidence": "high"
    },
    {
      "projectName": "Walcha Energy Project",
      "location": "Walcha, NSW (NE REZ)",
      "country": "Australia",
      "procurementStart": "Q1 2028",
      "procurementStatus": "Planning",
      "assetTypes": [
        "Wind",
        "Solar PV",
        "BESS",
        "Hydro",
        "HV Transmission",
        "REZ"
      ],
      "owner": "Walcha Energy (Consortium)",
      "epcContractor": "",
      "financiers": [],
      "projectValue": "AUD 5 billion+",
      "capacityMW": 2000,
      "mpEngagementWindow": "Engage H1 2026 – very long-term project, early positioning for major HV.",
      "mpServices": [
        "Technical Due Diligence",
        "QAQC Inspection"
      ],
      "priority": "Low",
      "sourceUrl": "walchaenergy.com.au",
      "summary": "Integrated RE hub (wind, solar, BESS, pumped hydro) within REZ. Extensive HV transmission/subs.",
      "statusNote": "Early stage development/feasibility studies ongoing. Walcha Energy Q2 2025.",
      "statusConfidence": "high"
    },
    {
      "projectName": "Ergon Energy Battery Storage Projects",
      "location": "Various regional QLD locations",
      "country": "Australia",
      "procurementStart": "Q2 2025",
      "procurementStatus": "Under Construction",
      "assetTypes": [
        "BESS",
        "Substation"
      ],
      "owner": "Ergon Energy (Energy Queensland)",
      "epcContractor": "UGL (example for some sites)",
      "financiers": [
        "Queensland Government"
      ],
      "projectValue": "AUD 200 million+",
      "capacityMW": 0,
      "mpEngagementWindow": "Engage now – ongoing QAQC for BESS and grid connection equipment.",
      "mpServices": [
        "QAQC Inspection",
        "Factory Acceptance Testing",
        "Site Supervision"
      ],
      "priority": "High",
      "sourceUrl": "ergon.com.au",
      "summary": "Multiple grid-connected BESS across regional QLD. Each site involves HV transformers/switchgear.",
      "statusNote": "Multiple projects under construction, ongoing rollout. Ergon Energy Q2 2025.",
      "statusConfidence": "high"
    },
    {
      "projectName": "Origin Energy Mortlake BESS",
      "location": "Mortlake, VIC",
      "country": "Australia",
      "procurementStart": "Q1 2024",
      "procurementStatus": "Under Construction",
      "assetTypes": [
        "BESS",
        "Substation"
      ],
      "owner": "Origin Energy",
      "epcContractor": "Doosan Enerbility",
      "financiers": [],
      "projectValue": "AUD 400 million",
      "capacityMW": 300,
      "mpEngagementWindow": "Immediate – FAT/QAQC for BESS units and grid connection equipment.",
      "mpServices": [
        "QAQC Inspection",
        "Factory Acceptance Testing",
        "Site Supervision"
      ],
      "priority": "High",
      "sourceUrl": "originenergy.com.au",
      "summary": "300MW / 600MWh BESS co-located with power station. New HV connections/substation upgrades.",
      "statusNote": "FID Q4 2023, construction active, mid-2026. Origin Energy Q2 2025.",
      "statusConfidence": "high"
    },
    {
      "projectName": "Kellyvale Solar Farm",
      "location": "Kellyvale, QLD",
      "country": "Australia",
      "procurementStart": "Q3 2027",
      "procurementStatus": "Planning",
      "assetTypes": [
        "Solar PV",
        "BESS",
        "Substation"
      ],
      "owner": "Vena Energy",
      "epcContractor": "",
      "financiers": [],
      "projectValue": "AUD 700 million",
      "capacityMW": 350,
      "mpEngagementWindow": "Engage H1 2026 – monitor for major permits/EPC tender announcements.",
      "mpServices": [
        "Technical Due Diligence",
        "QAQC Inspection"
      ],
      "priority": "Low",
      "sourceUrl": "venaenergy.com.au",
      "summary": "Proposed ~350MW solar farm + potential BESS. New substation/grid infrastructure, HV equipment.",
      "statusNote": "Environmental approval 2023, grid studies ongoing. Vena Energy Q2 2025.",
      "statusConfidence": "high"
    },
    {
      "projectName": "Hazelwood Battery Energy Storage System",
      "location": "Hazelwood, VIC",
      "country": "Australia",
      "procurementStart": "Q1 2025",
      "procurementStatus": "Under Construction",
      "assetTypes": [
        "BESS",
        "Substation"
      ],
      "owner": "ENGIE",
      "epcContractor": "Fluence",
      "financiers": [],
      "projectValue": "AUD 200 million",
      "capacityMW": 150,
      "mpEngagementWindow": "Engage H2 2025 – monitor for expansion plans/major maintenance cycles.",
      "mpServices": [
        "QAQC Inspection",
        "Factory Acceptance Testing",
        "Site Supervision"
      ],
      "priority": "Medium",
      "sourceUrl": "engie.com.au",
      "summary": "150MW / 150MWh BESS at former Hazelwood Power Station. Utilises existing HV infrastructure.",
      "statusNote": "Operational from Q4 2023, ongoing site works. ENGIE Q2 2025.",
      "statusConfidence": "high"
    },
    {
      "projectName": "Yooroonarra Wind Farm",
      "location": "Mid West, WA",
      "country": "Australia",
      "procurementStart": "Q4 2027",
      "procurementStatus": "Planning",
      "assetTypes": [
        "Wind",
        "HV Transmission",
        "Substation"
      ],
      "owner": "Alinta Energy",
      "epcContractor": "",
      "financiers": [],
      "projectValue": "AUD 2.0 billion+",
      "capacityMW": 1000,
      "mpEngagementWindow": "Engage H2 2026 – early engagement for EPC tender/substation design.",
      "mpServices": [
        "Technical Due Diligence",
        "QAQC Inspection"
      ],
      "priority": "Low",
      "sourceUrl": "alintaenergy.com.au",
      "summary": "Proposed 1GW wind farm. Requires new transmission lines/substations to SWIS, major HV equipment.",
      "statusNote": "Environmental approval process 2023, long-term development. Alinta Energy Q2 2025.",
      "statusConfidence": "high"
    },
    {
      "projectName": "Perth Data Centre - Digital Realty (PER2)",
      "location": "Perth, WA",
      "country": "Australia",
      "procurementStart": "Q2 2025",
      "procurementStatus": "Under Construction",
      "assetTypes": [
        "Data Centre",
        "Substation"
      ],
      "owner": "Digital Realty",
      "epcContractor": "",
      "financiers": [],
      "projectValue": "AUD 300 million+",
      "capacityMW": 0,
      "mpEngagementWindow": "Engage now – ongoing HV transformer/switchgear procurement for expansion.",
      "mpServices": [
        "QAQC Inspection",
        "Factory Acceptance Testing",
        "Site Supervision"
      ],
      "priority": "High",
      "sourceUrl": "digitalrealty.com",
      "summary": "Hyperscale data centre expansion, new/upgraded substations and HV electrical infrastructure. Continuous HV.",
      "statusNote": "Ongoing construction with new phases 2024-2025 delivery. Digital Realty Q2 2025.",
      "statusConfidence": "high"
    },
    {
      "projectName": "Melbourne Data Centre - Equinix (ME4/ME5)",
      "location": "Melbourne, VIC",
      "country": "Australia",
      "procurementStart": "Q3 2025",
      "procurementStatus": "Under Construction",
      "assetTypes": [
        "Data Centre",
        "Substation"
      ],
      "owner": "Equinix",
      "epcContractor": "",
      "financiers": [],
      "projectValue": "AUD 400 million+",
      "capacityMW": 0,
      "mpEngagementWindow": "Engage now – continuous procurement for HV equipment for new phases.",
      "mpServices": [
        "QAQC Inspection",
        "Factory Acceptance Testing",
        "Site Supervision"
      ],
      "priority": "High",
      "sourceUrl": "equinix.com",
      "summary": "Phased expansion of Equinix's Melbourne data centre. Requires HV upgrades and new HV infrastructure.",
      "statusNote": "Multiple phases under construction/announced 2024-2025. Equinix Q2 2025.",
      "statusConfidence": "high"
    },
    {
      "projectName": "Hydrogen Energy Supply Chain (HESC) Project",
      "location": "Latrobe Valley, VIC",
      "country": "Australia",
      "procurementStart": "Q4 2027",
      "procurementStatus": "Planning",
      "assetTypes": [
        "Hydrogen",
        "HV Transmission",
        "Substation"
      ],
      "owner": "Kawasaki Heavy Industries, J-Power, Iwatani Corp, Marubeni, Sumitomo, AGL, Woodside",
      "epcContractor": "",
      "financiers": [
        "Australian Government",
        "Victorian Government"
      ],
      "projectValue": "AUD 2.3 billion+",
      "capacityMW": 0,
      "mpEngagementWindow": "Engage H1 2026 – early engagement for future electrical systems.",
      "mpServices": [
        "Technical Due Diligence",
        "QAQC Inspection"
      ],
      "priority": "Low",
      "sourceUrl": "hesc.com",
      "summary": "Commercial scale-up green hydrogen production/export. Significant electrical infrastructure, HV substations.",
      "statusNote": "Pilot completed, commercialisation studies ongoing. HESC Q2 2025.",
      "statusConfidence": "high"
    },
    {
      "projectName": "Flinders Power Hub",
      "location": "Port Augusta, SA",
      "country": "Australia",
      "procurementStart": "Q1 2027",
      "procurementStatus": "Planning",
      "assetTypes": [
        "BESS",
        "Hydrogen",
        "Substation"
      ],
      "owner": "EnergyAustralia",
      "epcContractor": "",
      "financiers": [],
      "projectValue": "AUD 300 million+",
      "capacityMW": 225,
      "mpEngagementWindow": "Engage H2 2026 – early positioning for BESS and hydrogen facility equipment.",
      "mpServices": [
        "Technical Due Diligence",
        "QAQC Inspection"
      ],
      "priority": "Low",
      "sourceUrl": "energyaustralia.com.au",
      "summary": "Proposed 225MW/450MWh battery with potential hydrogen electrolyser. Significant HV connection infrastructure.",
      "statusNote": "Feasibility studies/approvals ongoing for 2027 start. EnergyAustralia Q2 2025.",
      "statusConfidence": "high"
    },
    {
      "projectName": "NQ Hydrogen Project",
      "location": "Townsville, QLD",
      "country": "Australia",
      "procurementStart": "Q4 2028",
      "procurementStatus": "Planning",
      "assetTypes": [
        "Hydrogen",
        "HV Transmission",
        "Substation"
      ],
      "owner": "Ark Energy (Korea Zinc subsidiary)",
      "epcContractor": "",
      "financiers": [],
      "projectValue": "AUD 1.0 billion+",
      "capacityMW": 0,
      "mpEngagementWindow": "Engage H1 2027 – early engagement for renewable integration/HV infrastructure.",
      "mpServices": [
        "Technical Due Diligence",
        "QAQC Inspection"
      ],
      "priority": "Low",
      "sourceUrl": "arkenergy.com.au",
      "summary": "Large-scale green hydrogen. Requires new renewable generation and associated HV transmission/substation upgrades.",
      "statusNote": "Feasibility studies ongoing, partnerships forming. Ark Energy Q2 2025.",
      "statusConfidence": "high"
    },
    {
      "projectName": "Bomen Solar Farm - BESS Expansion",
      "location": "Wagga Wagga, NSW",
      "country": "Australia",
      "procurementStart": "Q2 2024",
      "procurementStatus": "Under Construction",
      "assetTypes": [
        "BESS",
        "Substation"
      ],
      "owner": "Spark Infrastructure",
      "epcContractor": "GenusPlus",
      "financiers": [],
      "projectValue": "AUD 120 million",
      "capacityMW": 100,
      "mpEngagementWindow": "Immediate – BESS and associated substation equipment FAT/QAQC.",
      "mpServices": [
        "QAQC Inspection",
        "Factory Acceptance Testing",
        "Site Supervision"
      ],
      "priority": "High",
      "sourceUrl": "sparkinfrastructure.com",
      "summary": "100MW/200MWh BESS addition to Bomen Solar. Integration existing substation, new HV equipment.",
      "statusNote": "Construction active for 2025 operation. Spark Infrastructure Q2 2025.",
      "statusConfidence": "high"
    },
    {
      "projectName": "Central Coast Data Centre (various)",
      "location": "Central Coast, NSW",
      "country": "Australia",
      "procurementStart": "Q4 2026",
      "procurementStatus": "Planning",
      "assetTypes": [
        "Data Centre",
        "Substation"
      ],
      "owner": "Multiple Developers",
      "epcContractor": "",
      "financiers": [],
      "projectValue": "AUD 100 million+",
      "capacityMW": 0,
      "mpEngagementWindow": "Engage H1 2026 – monitor local planning for power needs.",
      "mpServices": [
        "Technical Due Diligence",
        "QAQC Inspection"
      ],
      "priority": "Low",
      "sourceUrl": "planningportal.nsw.gov.au",
      "summary": "Multiple proposed data centres. Require new local substations/grid upgrades, HV equipment.",
      "statusNote": "Various DAs for data centres active 2024. NSW Planning Portal Q2 2025.",
      "statusConfidence": "high"
    },
    {
      "projectName": "Serrinha Wind Farm Complex",
      "location": "Serrinha, BA",
      "country": "Brazil",
      "procurementStart": "Q1 2025",
      "procurementStatus": "Under Construction",
      "assetTypes": [
        "Wind",
        "Substation"
      ],
      "owner": "ENGIE Brasil Energia",
      "epcContractor": "Vestas (turbines), various BoP contractors",
      "financiers": [
        "BNB",
        "BNDES"
      ],
      "projectValue": "BRL 1.8 billion",
      "capacityMW": 350,
      "mpEngagementWindow": "Engage now – ongoing QAQC for turbines, substation, and transmission lines.",
      "mpServices": [
        "QAQC Inspection",
        "Factory Acceptance Testing",
        "Site Supervision"
      ],
      "priority": "High",
      "sourceUrl": "engie.com.br",
      "summary": "Large wind farm in Bahia. Multiple phases UC. New substations/transmission lines, significant HV equipment.",
      "statusNote": "Construction active, H1 2025 for some phases. ENGIE Brasil Q2 2025.",
      "statusConfidence": "high"
    },
    {
      "projectName": "Solar Project Cajuína",
      "location": "Piauí",
      "country": "Brazil",
      "procurementStart": "Q2 2025",
      "procurementStatus": "Under Construction",
      "assetTypes": [
        "Solar PV",
        "Substation"
      ],
      "owner": "Atlas Renewable Energy",
      "epcContractor": "",
      "financiers": [
        "IDB Invest"
      ],
      "projectValue": "BRL 1.5 billion",
      "capacityMW": 520,
      "mpEngagementWindow": "Engage now – specialist FAT/QAQC for sub and solar components.",
      "mpServices": [
        "QAQC Inspection",
        "Factory Acceptance Testing",
        "Site Supervision"
      ],
      "priority": "High",
      "sourceUrl": "atlasrenewableenergy.com",
      "summary": "Large 520MWp solar PV project. New grid connection, substation infrastructure, HV transformers/switchgear.",
      "statusNote": "Construction commenced Q4 2023, commercial Q4 2025. Atlas Renewable Q2 2025.",
      "statusConfidence": "high"
    },
    {
      "projectName": "Rio Grande do Norte Wind Farm Clusters (various)",
      "location": "Rio Grande do Norte",
      "country": "Brazil",
      "procurementStart": "Q3 2025",
      "procurementStatus": "Under Construction",
      "assetTypes": [
        "Wind",
        "Substation",
        "HV Transmission"
      ],
      "owner": "Multiple (e.g., Voltalia, EDP Renováveis)",
      "epcContractor": "Multiple turbine suppliers and BoP contractors",
      "financiers": [
        "BNDES",
        "BNB"
      ],
      "projectValue": "BRL 2.0 billion+",
      "capacityMW": 800,
      "mpEngagementWindow": "Immediate – multiple wind projects with ongoing turbine/substation FAT/QAQC.",
      "mpServices": [
        "QAQC Inspection",
        "Factory Acceptance Testing",
        "Site Supervision"
      ],
      "priority": "High",
      "sourceUrl": "abeeolica.org.br",
      "summary": "Ongoing development of multiple large-scale wind farm clusters. New substations/HV grid, constant HV equipment procurement.",
      "statusNote": "Several projects from recent ANEEL auctions UC for 2025-2026. ABEólica Q2 2025.",
      "statusConfidence": "high"
    },
    {
      "projectName": "Assú IV Solar Power Plant",
      "location": "Assú, RN",
      "country": "Brazil",
      "procurementStart": "Q4 2025",
      "procurementStatus": "Tender Active",
      "assetTypes": [
        "Solar PV",
        "Substation"
      ],
      "owner": "Canadian Solar",
      "epcContractor": "",
      "financiers": [],
      "projectValue": "BRL 600 million",
      "capacityMW": 200,
      "mpEngagementWindow": "Engage H2 2025 – pre-tender EPC, positioning for HV equipment inspection.",
      "mpServices": [
        "Technical Due Diligence",
        "QAQC Inspection"
      ],
      "priority": "Medium",
      "sourceUrl": "aneel.gov.br",
      "summary": "200MW solar power plant, winner in energy auction. Requires new substation and grid connection.",
      "statusNote": "Project authorized ANEEL, EPC tender mid-2025. CanalEnergia Q2 2025.",
      "statusConfidence": "high"
    },
    {
      "projectName": "Data Centre SC-01 (São Paulo)",
      "location": "São Paulo, SP",
      "country": "Brazil",
      "procurementStart": "Q2 2025",
      "procurementStatus": "Under Construction",
      "assetTypes": [
        "Data Centre",
        "Substation",
        "HV Transmission"
      ],
      "owner": "Ascenty (DigitalBridge)",
      "epcContractor": "",
      "financiers": [],
      "projectValue": "USD 200 million+",
      "capacityMW": 0,
      "mpEngagementWindow": "Immediate – HV electrical infrastructure/substation equipment QAQC for build.",
      "mpServices": [
        "QAQC Inspection",
        "Factory Acceptance Testing",
        "Site Supervision"
      ],
      "priority": "High",
      "sourceUrl": "ascenty.com",
      "summary": "New hyperscale data centre facility with power demands, necessitating new HV substations/grid connections.",
      "statusNote": "Construction ongoing with expansion phases 2024. Ascenty Q2 2025.",
      "statusConfidence": "high"
    },
    {
      "projectName": "Data Centre Expansion (Rio de Janeiro)",
      "location": "Rio de Janeiro, RJ",
      "country": "Brazil",
      "procurementStart": "Q3 2025",
      "procurementStatus": "Under Construction",
      "assetTypes": [
        "Data Centre",
        "Substation"
      ],
      "owner": "Scala Data Centers",
      "epcContractor": "",
      "financiers": [
        "BNP Paribas"
      ],
      "projectValue": "USD 150 million+",
      "capacityMW": 0,
      "mpEngagementWindow": "Engage now – continuous procurement for HV equipment for new phases.",
      "mpServices": [
        "QAQC Inspection",
        "Factory Acceptance Testing",
        "Site Supervision"
      ],
      "priority": "High",
      "sourceUrl": "scaladatacenters.com",
      "summary": "Expansion of hyperscale data centre, requiring further power capacity through new HV connections.",
      "statusNote": "Expansion projects under construction/planned 2024-2025. Scala Data Centers Q2 2025.",
      "statusConfidence": "high"
    },
    {
      "projectName": "Parque Eólico Campo Largo VII",
      "location": "Campo Largo, BA",
      "country": "Brazil",
      "procurementStart": "Q1 2025",
      "procurementStatus": "Under Construction",
      "assetTypes": [
        "Wind",
        "Substation"
      ],
      "owner": "Engie Brasil Energia",
      "epcContractor": "Nordex Acciona (turbines)",
      "financiers": [
        "BNDES"
      ],
      "projectValue": "BRL 700 million",
      "capacityMW": 120,
      "mpEngagementWindow": "Engage now – ongoing FAT/QAQC for wind turbines/substation components.",
      "mpServices": [
        "QAQC Inspection",
        "Factory Acceptance Testing",
        "Site Supervision"
      ],
      "priority": "High",
      "sourceUrl": "engie.com.br",
      "summary": "Expansion of Campo Largo wind complex, adding ~120MW. Integration existing substation, new HV equipment.",
      "statusNote": "Construction active, expected completion H2 2025. Engie Brasil Q2 2025.",
      "statusConfidence": "high"
    },
    {
      "projectName": "Pindaí I, II, III Solar",
      "location": "Pindaí, MG",
      "country": "Brazil",
      "procurementStart": "Q2 2025",
      "procurementStatus": "Under Construction",
      "assetTypes": [
        "Solar PV",
        "Substation"
      ],
      "owner": "Solatio Energia",
      "epcContractor": "",
      "financiers": [],
      "projectValue": "BRL 500 million",
      "capacityMW": 200,
      "mpEngagementWindow": "Engage now – ongoing QAQC for solar inverters, transformers, and substation.",
      "mpServices": [
        "QAQC Inspection",
        "Factory Acceptance Testing",
        "Site Supervision"
      ],
      "priority": "High",
      "sourceUrl": "solatioenergia.com.br",
      "summary": "Aggregate 200MW solar PV projects, requiring new grid connection/substation upgrades. HV equipment.",
      "statusNote": "Construction active for phased development, operation 2025. Solatio Energia Q2 2025.",
      "statusConfidence": "high"
    },
    {
      "projectName": "Aracatu Wind Farm",
      "location": "Aracatu, BA",
      "country": "Brazil",
      "procurementStart": "Q4 2025",
      "procurementStatus": "Tender Active",
      "assetTypes": [
        "Wind",
        "Substation"
      ],
      "owner": "AES Brasil",
      "epcContractor": "",
      "financiers": [],
      "projectValue": "BRL 800 million",
      "capacityMW": 150,
      "mpEngagementWindow": "Engage H2 2025 – EPC tender imminent, target HV equipment/turbine QAQC.",
      "mpServices": [
        "Technical Due Diligence",
        "QAQC Inspection"
      ],
      "priority": "Medium",
      "sourceUrl": "canalenergia.com.br",
      "summary": "150MW wind farm in Bahia, awarded. Construction mid-2025, involving new substations/HV grid.",
      "statusNote": "Project awarded/authorized, EPC tender mid-2025. CanalEnergia Q2 2025.",
      "statusConfidence": "high"
    },
    {
      "projectName": "Janaúba Solar Complex - Ongoing Phases",
      "location": "Janaúba, MG",
      "country": "Brazil",
      "procurementStart": "Q1 2025",
      "procurementStatus": "Under Construction",
      "assetTypes": [
        "Solar PV",
        "Substation"
      ],
      "owner": "Solatio Energia",
      "epcContractor": "",
      "financiers": [
        "Banco do Nordeste (BNB)"
      ],
      "projectValue": "BRL 3.0 billion+",
      "capacityMW": 1200,
      "mpEngagementWindow": "Immediate – continuous FAT/QAQC for solar inverters/substation expansions.",
      "mpServices": [
        "QAQC Inspection",
        "Factory Acceptance Testing",
        "Site Supervision"
      ],
      "priority": "High",
      "sourceUrl": "solatioenergia.com.br",
      "summary": "Latin America's largest solar complex, multiple phases UC. Continuous HV transformers/switchgear/substation procurement.",
      "statusNote": "Multiple phases operational/UC 2024-2025. Solatio Energia Q2 2025.",
      "statusConfidence": "high"
    },
    {
      "projectName": "Eólicas Umburanas Complex - Expansion",
      "location": "Umburanas, BA",
      "country": "Brazil",
      "procurementStart": "Q2 2025",
      "procurementStatus": "Under Construction",
      "assetTypes": [
        "Wind",
        "Substation"
      ],
      "owner": "Voltalia",
      "epcContractor": "Vestas (turbines)",
      "financiers": [
        "BNB"
      ],
      "projectValue": "BRL 1.0 billion+",
      "capacityMW": 600,
      "mpEngagementWindow": "Engage now – ongoing turbine/substation equipment QAQC for expansion.",
      "mpServices": [
        "QAQC Inspection",
        "Factory Acceptance Testing",
        "Site Supervision"
      ],
      "priority": "High",
      "sourceUrl": "voltalia.com",
      "summary": "Expansion phases of existing Umburanas wind complex. Integration existing grid, new HV equipment.",
      "statusNote": "Expansion phases under construction, completion 2025. Voltalia Q2 2025.",
      "statusConfidence": "high"
    },
    {
      "projectName": "Fotovoltaica Milagres",
      "location": "Milagres, CE",
      "country": "Brazil",
      "procurementStart": "Q1 2026",
      "procurementStatus": "Pre-tender",
      "assetTypes": [
        "Solar PV",
        "Substation"
      ],
      "owner": "EDP Renováveis",
      "epcContractor": "",
      "financiers": [],
      "projectValue": "BRL 450 million",
      "capacityMW": 180,
      "mpEngagementWindow": "Engage H2 2025 – pre-tender, positioning for HV equipment/solar inspection.",
      "mpServices": [
        "Technical Due Diligence",
        "QAQC Inspection"
      ],
      "priority": "Medium",
      "sourceUrl": "canalenergia.com.br",
      "summary": "180MW solar PV project awarded. Requires new substation/grid connection, involving HV equipment.",
      "statusNote": "Project authorized ANEEL, construction late 2025. CanalEnergia Q2 2025.",
      "statusConfidence": "high"
    },
    {
      "projectName": "Green Hydrogen Project Pecém",
      "location": "Pecém, CE",
      "country": "Brazil",
      "procurementStart": "Q3 2027",
      "procurementStatus": "Planning",
      "assetTypes": [
        "Hydrogen",
        "HV Transmission",
        "Substation"
      ],
      "owner": "Multiple International Consortia",
      "epcContractor": "",
      "financiers": [],
      "projectValue": "USD 5 billion+",
      "capacityMW": 0,
      "mpEngagementWindow": "Engage H1 2026 – long-term project, early positioning for large electrical systems.",
      "mpServices": [
        "Technical Due Diligence",
        "QAQC Inspection"
      ],
      "priority": "Low",
      "sourceUrl": "portodopecem.com.br",
      "summary": "Multiple large-scale green hydrogen projects. Requires new renewables, HV transmission/substation infrastructure.",
      "statusNote": "Numerous MOUs signed, feasibility studies ongoing post-2026. Port of Pecém Q2 2025.",
      "statusConfidence": "high"
    },
    {
      "projectName": "LT 500 kV Poções III - Padre Paraíso II",
      "location": "Bahia to Minas Gerais",
      "country": "Brazil",
      "procurementStart": "Q2 2025",
      "procurementStatus": "Under Construction",
      "assetTypes": [
        "HV Transmission",
        "Substation"
      ],
      "owner": "CPFL Energia",
      "epcContractor": "",
      "financiers": [
        "BNDES"
      ],
      "projectValue": "BRL 1.0 billion",
      "capacityMW": 0,
      "mpEngagementWindow": "Immediate – significant FAT/QAQC for 500kV transformers, circuit breakers.",
      "mpServices": [
        "QAQC Inspection",
        "Factory Acceptance Testing",
        "Site Supervision"
      ],
      "priority": "High",
      "sourceUrl": "aneel.gov.br",
      "summary": "300km new 500kV transmission line/substations, Bahia/Minas Gerais. Critical HV equipment.",
      "statusNote": "Project awarded 2023, construction active, completion by 2026. CanalEnergia Q2 2025.",
      "statusConfidence": "high"
    },
    {
      "projectName": "Solar Project Alex",
      "location": "Rio Grande do Norte",
      "country": "Brazil",
      "procurementStart": "Q1 2026",
      "procurementStatus": "Pre-tender",
      "assetTypes": [
        "Solar PV",
        "Substation"
      ],
      "owner": "Green Power (local developer)",
      "epcContractor": "",
      "financiers": [],
      "projectValue": "BRL 550 million",
      "capacityMW": 200,
      "mpEngagementWindow": "Engage H2 2025 – early positioning for EPC selection and HV component.",
      "mpServices": [
        "Technical Due Diligence",
        "QAQC Inspection"
      ],
      "priority": "Medium",
      "sourceUrl": "aneel.gov.br",
      "summary": "200MW solar PV project. Requires new substation/grid connection. HV transformers, switchgear.",
      "statusNote": "Project authorized ANEEL, EPC tender Q4 2025. CanalEnergia Q2 2025.",
      "statusConfidence": "high"
    },
    {
      "projectName": "Morro do Chapéu Sul II Wind Farm",
      "location": "Morro do Chapéu, BA",
      "country": "Brazil",
      "procurementStart": "Q2 2025",
      "procurementStatus": "Under Construction",
      "assetTypes": [
        "Wind",
        "Substation"
      ],
      "owner": "Engie Brasil Energia",
      "epcContractor": "Nordex Acciona (turbines)",
      "financiers": [
        "BNB"
      ],
      "projectValue": "BRL 1.8 billion",
      "capacityMW": 350,
      "mpEngagementWindow": "Engage now – ongoing QAQC for turbines and substation equipment.",
      "mpServices": [
        "QAQC Inspection",
        "Factory Acceptance Testing",
        "Site Supervision"
      ],
      "priority": "High",
      "sourceUrl": "engie.com.br",
      "summary": "Expansion Morro do Chapéu Sul wind farm (~350MW). Integration existing grid, new HV equipment.",
      "statusNote": "Construction active for expansion phase, completion H1 2025. Engie Brasil Q2 2025.",
      "statusConfidence": "high"
    },
    {
      "projectName": "Usinas Termelétrica Porto do Pecém (HV Infrastructure)",
      "location": "Porto do Pecém, CE",
      "country": "Brazil",
      "procurementStart": "Q1 2025",
      "procurementStatus": "Under Construction",
      "assetTypes": [
        "HV Transmission",
        "Substation"
      ],
      "owner": "Eneva",
      "epcContractor": "Mitsubish Power (turbines), various for balance of plant/transmission",
      "financiers": [
        "BNDES"
      ],
      "projectValue": "BRL 4.0 billion (HV portion significant)",
      "capacityMW": 0,
      "mpEngagementWindow": "Immediate – significant HV sub/transm equipment FAT/QAQC ongoing.",
      "mpServices": [
        "QAQC Inspection",
        "Factory Acceptance Testing",
        "Site Supervision"
      ],
      "priority": "High",
      "sourceUrl": "eneva.com.br",
      "summary": "1.4GW gas plant requiring substantial new 500kV substation/transmission. Critical HV equipment.",
      "statusNote": "Plant construction active, HV grid connection works for 2026. Eneva Q2 2025.",
      "statusConfidence": "high"
    },
    {
      "projectName": "Polo Solar Janaúba Complex - Expansion",
      "location": "Janaúba, MG",
      "country": "Brazil",
      "procurementStart": "Q2 2025",
      "procurementStatus": "Under Construction",
      "assetTypes": [
        "Solar PV",
        "Substation"
      ],
      "owner": "Solatio Energia",
      "epcContractor": "",
      "financiers": [
        "Banco do Nordeste (BNB)"
      ],
      "projectValue": "BRL 3.0 billion+",
      "capacityMW": 1200,
      "mpEngagementWindow": "Immediate – continuous FAT/QAQC for solar inverters/substation expansions.",
      "mpServices": [
        "QAQC Inspection",
        "Factory Acceptance Testing",
        "Site Supervision"
      ],
      "priority": "High",
      "sourceUrl": "solatioenergia.com.br",
      "summary": "Ongoing phased expansion Janaúba Solar Complex, with continuous new installations. Constant HV equipment.",
      "statusNote": "New phases continually commencing construction for 2025-2026. Solatio Energia Q2 2025.",
      "statusConfidence": "high"
    },
    {
      "projectName": "Datacenter ODATA Barueri Expansion",
      "location": "Barueri, SP",
      "country": "Brazil",
      "procurementStart": "Q2 2025",
      "procurementStatus": "Under Construction",
      "assetTypes": [
        "Data Centre",
        "Substation"
      ],
      "owner": "ODATA (Aligned Data Centers)",
      "epcContractor": "",
      "financiers": [],
      "projectValue": "USD 100 million+",
      "capacityMW": 0,
      "mpEngagementWindow": "Engage now – ongoing HV transformer/switchgear procurement for expansion.",
      "mpServices": [
        "QAQC Inspection",
        "Factory Acceptance Testing",
        "Site Supervision"
      ],
      "priority": "High",
      "sourceUrl": "odatacenters.com",
      "summary": "Phased expansion of ODATA's hyperscale data centre. Additional power infrastructure, new HV transformers/substation upgrades.",
      "statusNote": "Ongoing construction with new phases 2024-2025 delivery. ODATA Q2 2025.",
      "statusConfidence": "high"
    },
    {
      "projectName": "Usina Hidrelétrica de Itapebi (BESS/Modernization)",
      "location": "Itapebi, BA",
      "country": "Brazil",
      "procurementStart": "Q2 2027",
      "procurementStatus": "Planning",
      "assetTypes": [
        "BESS",
        "Substation"
      ],
      "owner": "Neoenergia",
      "epcContractor": "",
      "financiers": [],
      "projectValue": "BRL 200 million",
      "capacityMW": 0,
      "mpEngagementWindow": "Engage H2 2026 – monitor for BESS and substation upgrade tenders.",
      "mpServices": [
        "Technical Due Diligence",
        "QAQC Inspection"
      ],
      "priority": "Low",
      "sourceUrl": "neoenergia.com",
      "summary": "Planned BESS/modernization of Itapebi Hydroelectric. Upgrades to HV substation equipment and new HV.",
      "statusNote": "Neoenergia announced strategic focus on BESS/modernization 2024. CanalEnergia Q2 2025.",
      "statusConfidence": "high"
    },
    {
      "projectName": "NextDC S4 Melbourne (Moorabbin)",
      "location": "Moorabbin, VIC",
      "country": "Australia",
      "procurementStart": "Q4 2025",
      "procurementStatus": "Under Construction",
      "assetTypes": [
        "Data Centre",
        "Substation"
      ],
      "owner": "NextDC",
      "epcContractor": "Hutchinson Builders",
      "financiers": [],
      "projectValue": "AUD 1.5 billion+",
      "capacityMW": 150,
      "mpEngagementWindow": "Immediate – HV equipment QAQC for phased construction.",
      "mpServices": [
        "QAQC Inspection",
        "Factory Acceptance Testing",
        "Site Supervision"
      ],
      "priority": "High",
      "sourceUrl": "nextdc.com",
      "summary": "Hyperscale data centre, phased development. New HV substation/grid connections. HV transformers.",
      "statusNote": "Construction active, phased build 2024-2025. NextDC Q2 2025.",
      "statusConfidence": "high"
    },
    {
      "projectName": "Microsoft Data Centre Expansion (VIC)",
      "location": "Melbourne Metropolitan Area, VIC",
      "country": "Australia",
      "procurementStart": "Q3 2025",
      "procurementStatus": "Under Construction",
      "assetTypes": [
        "Data Centre",
        "Substation"
      ],
      "owner": "Microsoft",
      "epcContractor": "",
      "financiers": [],
      "projectValue": "AUD 500 million+",
      "capacityMW": 0,
      "mpEngagementWindow": "Engage now – continuous procurement of HV transformers, switchgear.",
      "mpServices": [
        "QAQC Inspection",
        "Factory Acceptance Testing",
        "Site Supervision"
      ],
      "priority": "High",
      "sourceUrl": "datacenterdynamics.com",
      "summary": "Phased expansion of Microsoft data centre footprint in VIC, necessitating new substations/HV grid.",
      "statusNote": "Multiple construction phases reported 2024-2025. DCD Q2 2025.",
      "statusConfidence": "high"
    },
    {
      "projectName": "Google Cloud Data Centre (Sydney West)",
      "location": "Western Sydney, NSW (Eastern Creek)",
      "country": "Australia",
      "procurementStart": "Q4 2025",
      "procurementStatus": "Under Construction",
      "assetTypes": [
        "Data Centre",
        "Substation"
      ],
      "owner": "Google",
      "epcContractor": "",
      "financiers": [],
      "projectValue": "AUD 1 billion+",
      "capacityMW": 0,
      "mpEngagementWindow": "Engage H2 2025 – ongoing HV equipment procurement for power infrastructure.",
      "mpServices": [
        "QAQC Inspection",
        "Factory Acceptance Testing",
        "Site Supervision"
      ],
      "priority": "High",
      "sourceUrl": "datacenterdynamics.com",
      "summary": "Hyperscale data centre, requiring significant new high-voltage grid connection and substations. Continuous HV.",
      "statusNote": "Phased construction underway, significant capacity announced. DCD Q2 2025.",
      "statusConfidence": "high"
    },
    {
      "projectName": "Vantage Data Centers (Sydney SNG1)",
      "location": "Western Sydney, NSW (Horsley Park)",
      "country": "Australia",
      "procurementStart": "Q3 2025",
      "procurementStatus": "Under Construction",
      "assetTypes": [
        "Data Centre",
        "Substation"
      ],
      "owner": "Vantage Data Centers",
      "epcContractor": "",
      "financiers": [],
      "projectValue": "AUD 1 billion+",
      "capacityMW": 0,
      "mpEngagementWindow": "Immediate – ongoing HV equipment procurement for power infrastructure.",
      "mpServices": [
        "QAQC Inspection",
        "Factory Acceptance Testing",
        "Site Supervision"
      ],
      "priority": "High",
      "sourceUrl": "vantage-dc.com",
      "summary": "Large hyperscale data centre campus, requiring new high-voltage substations/complex grid connections. Continuous HV.",
      "statusNote": "Phased construction ongoing, expansion plans active. Vantage DC Q2 2025.",
      "statusConfidence": "high"
    },
    {
      "projectName": "Equinix SY8 (Sydney)",
      "location": "Eastern Creek, NSW",
      "country": "Australia",
      "procurementStart": "Q4 2025",
      "procurementStatus": "Under Construction",
      "assetTypes": [
        "Data Centre",
        "Substation"
      ],
      "owner": "Equinix",
      "epcContractor": "",
      "financiers": [],
      "projectValue": "AUD 200 million+",
      "capacityMW": 0,
      "mpEngagementWindow": "Engage H2 2025 – ongoing HV equipment procurement for power delivery.",
      "mpServices": [
        "QAQC Inspection",
        "Factory Acceptance Testing",
        "Site Supervision"
      ],
      "priority": "High",
      "sourceUrl": "equinix.com",
      "summary": "Expansion of Equinix Sydney data centre, requiring significant power infrastructure upgrades including new HV.",
      "statusNote": "Construction active with phased deployments. Equinix Q2 2025.",
      "statusConfidence": "high"
    },
    {
      "projectName": "DC Two (Perth Data Centre 2)",
      "location": "Perth, WA",
      "country": "Australia",
      "procurementStart": "Q1 2026",
      "procurementStatus": "Planning",
      "assetTypes": [
        "Data Centre",
        "Substation"
      ],
      "owner": "DC Two",
      "epcContractor": "",
      "financiers": [],
      "projectValue": "AUD 50 million+",
      "capacityMW": 0,
      "mpEngagementWindow": "Engage H1 2026 – monitor for planning approvals/substation tenders.",
      "mpServices": [
        "Technical Due Diligence",
        "QAQC Inspection"
      ],
      "priority": "Low",
      "sourceUrl": "dctwo.com.au",
      "summary": "Proposed data centre expansion. Requires new substation capacity/grid upgrades, involving HV equipment.",
      "statusNote": "Planning approvals for expansion underway. DC Two Q2 2025.",
      "statusConfidence": "high"
    },
    {
      "projectName": "QLD Data Centre (Murarrie)",
      "location": "Murarrie, QLD",
      "country": "Australia",
      "procurementStart": "Q3 2026",
      "procurementStatus": "Planning",
      "assetTypes": [
        "Data Centre",
        "Substation"
      ],
      "owner": "TBD (Hyperscale Developer)",
      "epcContractor": "",
      "financiers": [],
      "projectValue": "AUD 300 million+",
      "capacityMW": 0,
      "mpEngagementWindow": "Engage H2 2026 – early planning grid connection/substation development.",
      "mpServices": [
        "Technical Due Diligence",
        "QAQC Inspection"
      ],
      "priority": "Low",
      "sourceUrl": "planning.brisbane.qld.gov.au",
      "summary": "Large-scale data centre proposed. Requires new dedicated substation/grid connections. HV equipment.",
      "statusNote": "Development application lodged 2024. Brisbane Council Planning Q2 2025.",
      "statusConfidence": "medium"
    },
    {
      "projectName": "Sydney Data Centre (Kemps Creek)",
      "location": "Kemps Creek, NSW",
      "country": "Australia",
      "procurementStart": "Q4 2026",
      "procurementStatus": "Planning",
      "assetTypes": [
        "Data Centre",
        "Substation"
      ],
      "owner": "TBD (Developer)",
      "epcContractor": "",
      "financiers": [],
      "projectValue": "AUD 200 million+",
      "capacityMW": 0,
      "mpEngagementWindow": "Engage H1 2027 – monitor for planning approvals/power infrastructure tenders.",
      "mpServices": [
        "Technical Due Diligence",
        "QAQC Inspection"
      ],
      "priority": "Low",
      "sourceUrl": "planningportal.nsw.gov.au",
      "summary": "Proposed data centre at Kemps Creek, targeting future expansion. New substation/HV grid upgrades.",
      "statusNote": "Early planning applications 2024 for masterplan. NSW Planning Portal Q2 2025.",
      "statusConfidence": "medium"
    },
    {
      "projectName": "Port Hedland Solar and BESS",
      "location": "Port Hedland, WA",
      "country": "Australia",
      "procurementStart": "Q1 2026",
      "procurementStatus": "Pre-tender",
      "assetTypes": [
        "Solar PV",
        "BESS",
        "Substation",
        "HV Transmission"
      ],
      "owner": "Pilbara Energy (Horizon Power)",
      "epcContractor": "",
      "financiers": [
        "WA Government"
      ],
      "projectValue": "AUD 300 million",
      "capacityMW": 100,
      "mpEngagementWindow": "Engage H2 2025 – pre-tender activities for EPC and HV equipment.",
      "mpServices": [
        "Technical Due Diligence",
        "QAQC Inspection"
      ],
      "priority": "Medium",
      "sourceUrl": "horizonpower.com.au",
      "summary": "Proposed 100MW solar farm + BESS, requiring new high-voltage transmission/substation infrastructure.",
      "statusNote": "Feasibility studies ongoing, expected FID 2025. Horizon Power Q2 2025.",
      "statusConfidence": "high"
    },
    {
      "projectName": "Collie Battery 2",
      "location": "Collie, WA",
      "country": "Australia",
      "procurementStart": "Q3 2025",
      "procurementStatus": "Tender Active",
      "assetTypes": [
        "BESS",
        "Substation"
      ],
      "owner": "Synergy",
      "epcContractor": "",
      "financiers": [
        "WA Government"
      ],
      "projectValue": "AUD 500 million",
      "capacityMW": 500,
      "mpEngagementWindow": "Immediate – active tender for EPC/BESS. Specialist QAQC.",
      "mpServices": [
        "QAQC Inspection",
        "Factory Acceptance Testing",
        "Site Supervision"
      ],
      "priority": "High",
      "sourceUrl": "reneweconomy.com.au",
      "summary": "Proposed 500MW BESS at Collie, expanding existing grid connection. HV transformers/switchgear.",
      "statusNote": "State government commitment 2023, tender active. RenewEconomy Q2 2025.",
      "statusConfidence": "high"
    },
    {
      "projectName": "Canto Grande Wind Farm",
      "location": "Rio Grande do Norte",
      "country": "Brazil",
      "procurementStart": "Q3 2025",
      "procurementStatus": "Under Construction",
      "assetTypes": [
        "Wind",
        "Substation",
        "HV Transmission"
      ],
      "owner": "Voltalia",
      "epcContractor": "",
      "financiers": [],
      "projectValue": "BRL 900 million",
      "capacityMW": 200,
      "mpEngagementWindow": "Engage now – ongoing QAQC for turbines, sub, grid connection.",
      "mpServices": [
        "QAQC Inspection",
        "Factory Acceptance Testing",
        "Site Supervision"
      ],
      "priority": "High",
      "sourceUrl": "voltalia.com",
      "summary": "New 200MW wind farm. Requires new substation and HV transmission line to national grid.",
      "statusNote": "Awarded ANEEL auction, construction for 2025 operation. Voltalia Q2 2025.",
      "statusConfidence": "high"
    },
    {
      "projectName": "Serra das Almas Solar",
      "location": "Bahia",
      "country": "Brazil",
      "procurementStart": "Q1 2026",
      "procurementStatus": "Pre-tender",
      "assetTypes": [
        "Solar PV",
        "Substation"
      ],
      "owner": "AES Brasil",
      "epcContractor": "",
      "financiers": [],
      "projectValue": "BRL 700 million",
      "capacityMW": 250,
      "mpEngagementWindow": "Engage H2 2025 – pre-tender EPC, positioning for HV equipment/solar inspection.",
      "mpServices": [
        "Technical Due Diligence",
        "QAQC Inspection"
      ],
      "priority": "Medium",
      "sourceUrl": "canalenergia.com.br",
      "summary": "Proposed 250MW solar PV project. Requires new substation/grid connection. HV transformers/switchgear.",
      "statusNote": "Project authorized ANEEL, EPC tender Q4 2025. CanalEnergia Q2 2025.",
      "statusConfidence": "high"
    },
    {
      "projectName": "Central Highlands Wind Farm",
      "location": "Central Highlands, QLD",
      "country": "Australia",
      "procurementStart": "Q3 2027",
      "procurementStatus": "Planning",
      "assetTypes": [
        "Wind",
        "Substation"
      ],
      "owner": "TBD",
      "epcContractor": "",
      "financiers": [],
      "projectValue": "AUD 1.0 billion+",
      "capacityMW": 600,
      "mpEngagementWindow": "Engage H1 2026 – early planning for grid connection and HV assets.",
      "mpServices": [
        "Technical Due Diligence",
        "QAQC Inspection"
      ],
      "priority": "Low",
      "sourceUrl": "cleanenergycouncil.org.au",
      "summary": "Proposed 600MW wind farm. Requires new substation and grid connection, involves HV equipment.",
      "statusNote": "EIS submission active 2024. Clean Energy Council Q2 2025.",
      "statusConfidence": "high"
    },
    {
      "projectName": "Yatala Solar Farm",
      "location": "Central Queensland, QLD",
      "country": "Australia",
      "procurementStart": "Q2 2027",
      "procurementStatus": "Planning",
      "assetTypes": [
        "Solar PV",
        "BESS",
        "Substation"
      ],
      "owner": "Origin Energy",
      "epcContractor": "",
      "financiers": [],
      "projectValue": "AUD 600 million",
      "capacityMW": 300,
      "mpEngagementWindow": "Engage H1 2026 – early engagement for substation design and BESS.",
      "mpServices": [
        "Technical Due Diligence",
        "QAQC Inspection"
      ],
      "priority": "Medium",
      "sourceUrl": "originenergy.com.au",
      "summary": "Proposed 300MW solar PV + 150MW BESS. Requires new substation/grid connection with HV equipment.",
      "statusNote": "Project assessment underway 2024. Origin Energy Q2 2025.",
      "statusConfidence": "high"
    },
    {
      "projectName": "Microsoft Data Centre (Canberra)",
      "location": "Canberra, ACT",
      "country": "Australia",
      "procurementStart": "Q3 2024",
      "procurementStatus": "Under Construction",
      "assetTypes": [
        "Data Centre",
        "Substation"
      ],
      "owner": "Microsoft",
      "epcContractor": "",
      "financiers": [],
      "projectValue": "AUD 500 million+",
      "capacityMW": 0,
      "mpEngagementWindow": "Engage now – ongoing HV equipment QAQC for phased delivery.",
      "mpServices": [
        "QAQC Inspection",
        "Factory Acceptance Testing",
        "Site Supervision"
      ],
      "priority": "High",
      "sourceUrl": "datacenterdynamics.com",
      "summary": "New multi-region data centre. Requires HV substations, grid connections, HV equipment procurement.",
      "statusNote": "Construction active, phased rollout 2024-2025. DCD Q2 2025.",
      "statusConfidence": "high"
    },
    {
      "projectName": "Macquarie Data Centre (Sydney North)",
      "location": "Sydney North, NSW",
      "country": "Australia",
      "procurementStart": "Q2 2026",
      "procurementStatus": "Planning",
      "assetTypes": [
        "Data Centre",
        "Substation"
      ],
      "owner": "Macquarie Data Centres",
      "epcContractor": "",
      "financiers": [],
      "projectValue": "AUD 300 million+",
      "capacityMW": 0,
      "mpEngagementWindow": "Engage H2 2025 – early engagement for HV power supply design.",
      "mpServices": [
        "Technical Due Diligence",
        "QAQC Inspection"
      ],
      "priority": "Medium",
      "sourceUrl": "datacenterdynamics.com",
      "summary": "New hyperscale data centre. Requires significant HV power infrastructure, new substation/upgrades.",
      "statusNote": "Planning approval 2024 for construction. DCD Q2 2025.",
      "statusConfidence": "high"
    },
    {
      "projectName": "Amazon Web Services (AWS) Data Centre (VIC)",
      "location": "Melbourne Metropolitan Area, VIC",
      "country": "Australia",
      "procurementStart": "Q1 2025",
      "procurementStatus": "Under Construction",
      "assetTypes": [
        "Data Centre",
        "Substation"
      ],
      "owner": "Amazon Web Services",
      "epcContractor": "",
      "financiers": [],
      "projectValue": "AUD 500 million+",
      "capacityMW": 0,
      "mpEngagementWindow": "Engage now – ongoing HV equipment procurement for multiple sites.",
      "mpServices": [
        "QAQC Inspection",
        "Factory Acceptance Testing",
        "Site Supervision"
      ],
      "priority": "High",
      "sourceUrl": "datacenterdynamics.com",
      "summary": "Multiple AWS data centres. Requires substantial power infrastructure, new HV substations.",
      "statusNote": "Construction active, expansion phases 2024-2025. DCD Q2 2025.",
      "statusConfidence": "high"
    },
    {
      "projectName": "Digital Realty SYD5 (Sydney)",
      "location": "Western Sydney, NSW",
      "country": "Australia",
      "procurementStart": "Q1 2026",
      "procurementStatus": "Planning",
      "assetTypes": [
        "Data Centre",
        "Substation"
      ],
      "owner": "Digital Realty",
      "epcContractor": "",
      "financiers": [],
      "projectValue": "AUD 400 million+",
      "capacityMW": 0,
      "mpEngagementWindow": "Engage H2 2025 – monitor for planning approvals, HV equipment.",
      "mpServices": [
        "Technical Due Diligence",
        "QAQC Inspection"
      ],
      "priority": "Medium",
      "sourceUrl": "digitalrealty.com",
      "summary": "Hyperscale data centre expansion, new/upgraded HV power infrastructure for increased capacity.",
      "statusNote": "Planning applications active 2024. Digital Realty Q2 2025.",
      "statusConfidence": "high"
    },
    {
      "projectName": "NextDC B2 Brisbane (Darra)",
      "location": "Darra, QLD",
      "country": "Australia",
      "procurementStart": "Q3 2026",
      "procurementStatus": "Planning",
      "assetTypes": [
        "Data Centre",
        "Substation"
      ],
      "owner": "NextDC",
      "epcContractor": "",
      "financiers": [],
      "projectValue": "AUD 250 million+",
      "capacityMW": 0,
      "mpEngagementWindow": "Engage H1 2026 – early positioning for HV equipment.",
      "mpServices": [
        "Technical Due Diligence",
        "QAQC Inspection"
      ],
      "priority": "Medium",
      "sourceUrl": "nextdc.com",
      "summary": "Hyperscale data centre, phased development. Requires new HV substation and grid connections.",
      "statusNote": "Planning approval granted 2024. NextDC Q2 2025.",
      "statusConfidence": "high"
    },
    {
      "projectName": "Serra do Tigre Wind Farm",
      "location": "Rio Grande do Norte",
      "country": "Brazil",
      "procurementStart": "Q3 2026",
      "procurementStatus": "Pre-tender",
      "assetTypes": [
        "Wind",