{
  "projects": [
    {
      "projectName": "Central-West Orana REZ Transmission Infrastructure",
      "location": "Central-West Orana, New South Wales",
      "country": "Australia",
      "procurementStart": "Q4 2023",
      "procurementStatus": "Tender Active",
      "assetTypes": [
        "REZ",
        "HV Transmission",
        "Substation",
        "HV Transformers",
        "HV Circuit Breakers",
        "GIS"
      ],
      "companies": [
        "EnergyCo NSW",
        "Transgrid"
      ],
      "fundingSources": [
        "NSW Government"
      ],
      "projectValue": "AUD 3.2 billion",
      "capacityMW": 0,
      "mpEngagementWindow": "Q3 2024 - Q4 2026",
      "mpServices": [
        "Factory Acceptance Testing",
        "QAQC Inspection",
        "Site Supervision",
        "Vendor Assessment"
      ],
      "priority": "High",
      "sourceUrl": "https://www.energyco.nsw.gov.au/renewable-energy-zones/central-west-orana-rez",
      "summary": "Development of critical transmission infrastructure for the Central-West Orana REZ, including new high-voltage transmission lines, substations, and associated HV equipment to connect new generation to the grid. Procurement for various packages is ongoing or imminent."
    },
    {
      "projectName": "New England REZ Transmission Infrastructure",
      "location": "New England, New South Wales",
      "country": "Australia",
      "procurementStart": "Q1 2024",
      "procurementStatus": "Tender Active",
      "assetTypes": [
        "REZ",
        "HV Transmission",
        "Substation",
        "HV Transformers",
        "HV Circuit Breakers",
        "GIS"
      ],
      "companies": [
        "EnergyCo NSW",
        "Transgrid"
      ],
      "fundingSources": [
        "NSW Government"
      ],
      "projectValue": "AUD 2.7 billion",
      "capacityMW": 0,
      "mpEngagementWindow": "Q4 2024 - Q4 2026",
      "mpServices": [
        "Factory Acceptance Testing",
        "QAQC Inspection",
        "Site Supervision",
        "Vendor Assessment"
      ],
      "priority": "High",
      "sourceUrl": "https://www.energyco.nsw.gov.au/renewable-energy-zones/new-england-rez",
      "summary": "Key transmission infrastructure to unlock the New England REZ, involving new high-voltage lines, new and upgraded substations, and significant HV equipment. Tender processes for various stages of procurement are active or expected shortly."
    },
    {
      "projectName": "Hunter-Central Coast REZ Transmission Infrastructure",
      "location": "Hunter-Central Coast, New South Wales",
      "country": "Australia",
      "procurementStart": "Q2 2024",
      "procurementStatus": "Planning",
      "assetTypes": [
        "REZ",
        "HV Transmission",
        "Substation",
        "HV Transformers",
        "HV Circuit Breakers"
      ],
      "companies": [
        "EnergyCo NSW"
      ],
      "fundingSources": [
        "NSW Government"
      ],
      "projectValue": "AUD 2 billion+",
      "capacityMW": 0,
      "mpEngagementWindow": "Q1 2025 - Q4 2027",
      "mpServices": [
        "Factory Acceptance Testing",
        "QAQC Inspection",
        "Vendor Assessment",
        "Technical Due Diligence"
      ],
      "priority": "Medium",
      "sourceUrl": "https://www.energyco.nsw.gov.au/renewable-energy-zones/hunter-central-coast-rez",
      "summary": "Early planning and community engagement for the Hunter-Central Coast REZ transmission infrastructure. Initial procurement for network capacity and access is underway, with major HV equipment procurement expected in the next 12-18 months."
    },
    {
      "projectName": "VNI West Interconnector (KerangLink)",
      "location": "Victoria to New South Wales",
      "country": "Australia",
      "procurementStart": "Q3 2024",
      "procurementStatus": "Planning",
      "assetTypes": [
        "HV Transmission",
        "Substation",
        "HV Transformers",
        "HV Circuit Breakers",
        "GIS"
      ],
      "companies": [
        "AEMO",
        "Transgrid",
        "AusNet Services"
      ],
      "fundingSources": [
        "Australian Government",
        "State Governments"
      ],
      "projectValue": "AUD 3.3 billion",
      "capacityMW": 0,
      "mpEngagementWindow": "Q4 2024 - Q4 2028",
      "mpServices": [
        "Factory Acceptance Testing",
        "QAQC Inspection",
        "Site Supervision",
        "Vendor Assessment"
      ],
      "priority": "High",
      "sourceUrl": "https://www.aemo.com.au/energy-systems/major-programs/integrated-system-plan-isp/vni-west",
      "summary": "A major new 500 kV transmission link between Victoria and NSW to increase interconnector capacity. The project is advancing through regulatory approvals, with major procurement for HV components and EPC contractors anticipated to commence in late 2024."
    },
    {
      "projectName": "Lismore BESS Project",
      "location": "Lismore, New South Wales",
      "country": "Australia",
      "procurementStart": "Q4 2023",
      "procurementStatus": "Under Construction",
      "assetTypes": [
        "BESS",
        "Substation",
        "HV Circuit Breakers"
      ],
      "companies": [
        "FTP Digital (Fluence)",
        "Lismore City Council"
      ],
      "fundingSources": [
        "NSW Government",
        "CEFC"
      ],
      "projectValue": "AUD 200 million",
      "capacityMW": 120,
      "mpEngagementWindow": "Q3 2024 - Q1 2025",
      "mpServices": [
        "Factory Acceptance Testing",
        "QAQC Inspection",
        "Site Supervision"
      ],
      "priority": "High",
      "sourceUrl": "https://www.pv-magazine-australia.com/2023/12/11/120-mw-battery-switched-on-in-nsw-amid-flooding-and-bushfires/",
      "summary": "A 120MW / 240MWh grid-scale BESS project. While major construction is underway, final component installations and commissioning inspections, particularly for substation equipment and grid connection apparatus, are still to occur in 2024."
    },
    {
      "projectName": "Bulli Creek Solar Farm & BESS (Stage 2)",
      "location": "Bulli Creek, Queensland",
      "country": "Australia",
      "procurementStart": "Q1 2024",
      "procurementStatus": "Planning",
      "assetTypes": [
        "Solar PV",
        "BESS",
        "Substation",
        "HV Transformers"
      ],
      "companies": [
        "Terregra Renewables"
      ],
      "fundingSources": [
        "Private Investment"
      ],
      "projectValue": "AUD 1.5 billion",
      "capacityMW": 800,
      "mpEngagementWindow": "Q4 2024 - Q4 2026",
      "mpServices": [
        "Vendor Assessment",
        "Factory Acceptance Testing",
        "QAQC Inspection",
        "Technical Due Diligence"
      ],
      "priority": "Medium",
      "sourceUrl": "https://reneweconomy.com.au/terregra-unveils-800mw-battery-for-bulli-creek-solar-farm-in-queensland/",
      "summary": "Expansion of the Bulli Creek Renewable Energy Hub, including an 800MW BESS and significant solar PV. The project is in advanced planning, with EPC and major equipment procurement, including new substation components, expected to ramp up in late 2024."
    },
    {
      "projectName": "Collgar II Wind Farm Expansion",
      "location": "Merredin, Western Australia",
      "country": "Australia",
      "procurementStart": "Q1 2024",
      "procurementStatus": "Planning",
      "assetTypes": [
        "Wind",
        "Substation",
        "HV Transformers",
        "HV Circuit Breakers"
      ],
      "companies": [
        "Collgar Wind Farm"
      ],
      "fundingSources": [
        "Private Investment"
      ],
      "projectValue": "AUD 500 million",
      "capacityMW": 200,
      "mpEngagementWindow": "Q4 2024 - Q3 2026",
      "mpServices": [
        "Factory Acceptance Testing",
        "QAQC Inspection",
        "Vendor Assessment"
      ],
      "priority": "Medium",
      "sourceUrl": "https://www.pv-magazine-australia.com/2024/02/19/collgar-eyes-massive-expansion-of-wa-wind-farm/",
      "summary": "Proposed expansion of the existing Collgar Wind Farm with an additional 200 MW of capacity. The project is undergoing approvals, with major equipment and grid connection upgrades, including new substation components, to be procured from late 2024."
    },
    {
      "projectName": "Hunter Hydrogen Hub Development",
      "location": "Hunter Valley, New South Wales",
      "country": "Australia",
      "procurementStart": "Q2 2024",
      "procurementStatus": "Planning",
      "assetTypes": [
        "Hydrogen",
        "Substation",
        "HV Transmission"
      ],
      "companies": [
        "AGL",
        "Fortescue Future Industries",
        "Origin Energy",
        "EnergyCo NSW"
      ],
      "fundingSources": [
        "ARENA",
        "NSW Government",
        "Private Investment"
      ],
      "projectValue": "AUD 1 billion+",
      "capacityMW": 0,
      "mpEngagementWindow": "Q1 2025 - Q4 2027",
      "mpServices": [
        "Technical Due Diligence",
        "Vendor Assessment",
        "Factory Acceptance Testing",
        "QAQC Inspection"
      ],
      "priority": "Medium",
      "sourceUrl": "https://arena.gov.au/projects/hunter-hydrogen-hub/",
      "summary": "Development of a large-scale green hydrogen production and export hub. While early stages for full development, significant electrical infrastructure, including potential new substations and grid connections, will be required, with tenders expected in 2025."
    },
    {
      "projectName": "Port Augusta Green Hydrogen Project",
      "location": "Port Augusta, South Australia",
      "country": "Australia",
      "procurementStart": "Q3 2024",
      "procurementStatus": "Planning",
      "assetTypes": [
        "Hydrogen",
        "Wind",
        "Solar PV",
        "BESS",
        "Substation",
        "HV Transmission"
      ],
      "companies": [
        "AGL"
      ],
      "fundingSources": [
        "SA Government",
        "ARENA",
        "Private Investment"
      ],
      "projectValue": "AUD 1.3 billion",
      "capacityMW": 250,
      "mpEngagementWindow": "Q4 2024 - Q4 2027",
      "mpServices": [
        "Technical Due Diligence",
        "Vendor Assessment",
        "Factory Acceptance Testing",
        "QAQC Inspection",
        "Site Supervision"
      ],
      "priority": "Medium",
      "sourceUrl": "https://www.reneweconomy.com.au/agl-unveils-plans-for-250mw-electrolyser-and-green-hydrogen-hub-at-port-augusta/",
      "summary": "A major green hydrogen production facility co-located with new wind/solar generation and BESS. The project is in feasibility and design, with significant procurement for electrolysers, renewable generation, and associated HV grid infrastructure expected to commence in 2024-2025."
    },
    {
      "projectName": "Kiamal Solar Farm Stage 2 & BESS",
      "location": "Ouyen, Victoria",
      "country": "Australia",
      "procurementStart": "Q4 2023",
      "procurementStatus": "Under Construction",
      "assetTypes": [
        "Solar PV",
        "BESS",
        "Substation",
        "HV Transformers"
      ],
      "companies": [
        "TotalEnergies",
        "Lyon Group"
      ],
      "fundingSources": [
        "CEFC",
        "Private Investment"
      ],
      "projectValue": "AUD 500 million",
      "capacityMW": 150,
      "mpEngagementWindow": "Q3 2024 - Q2 2025",
      "mpServices": [
        "QAQC Inspection",
        "Factory Acceptance Testing",
        "Site Supervision"
      ],
      "priority": "High",
      "sourceUrl": "https://www.cleanenergyfinancecorp.com.au/projects/project-detail/kiamal-solar-farm/",
      "summary": "Expansion of the Kiamal Solar Farm with additional PV and a large-scale BESS. Construction is underway, with specialist procurement and inspection for substation upgrades, new battery inverters, and grid connection equipment ongoing or imminent for commissioning."
    },
    {
      "projectName": "Port Hedland Green Hydrogen Hub",
      "location": "Port Hedland, Western Australia",
      "country": "Australia",
      "procurementStart": "Q1 2024",
      "procurementStatus": "Planning",
      "assetTypes": [
        "Hydrogen",
        "Solar PV",
        "Wind",
        "Substation",
        "HV Transmission"
      ],
      "companies": [
        "Fortescue Future Industries",
        "BP"
      ],
      "fundingSources": [
        "Western Australian Government",
        "Private Investment"
      ],
      "projectValue": "AUD 10 billion+",
      "capacityMW": 0,
      "mpEngagementWindow": "Q2 2025 - Q4 2028",
      "mpServices": [
        "Technical Due Diligence",
        "Vendor Assessment",
        "Factory Acceptance Testing",
        "QAQC Inspection",
        "Site Supervision"
      ],
      "priority": "Medium",
      "sourceUrl": "https://www.fortescue.com/news/2024/port-hedland-green-hydrogen",
      "summary": "A massive green hydrogen production and export facility, integrating significant new renewable energy generation (solar/wind) and requiring substantial new HV grid infrastructure. The project is in feasibility and design, with major procurement rounds anticipated from late 2025."
    },
    {
      "projectName": "Victoria-New South Wales Interconnector West (VNI West)",
      "location": "Western Victoria to South-West NSW",
      "country": "Australia",
      "procurementStart": "Q3 2024",
      "procurementStatus": "Planning",
      "assetTypes": [
        "HV Transmission",
        "Substation",
        "HV Transformers",
        "HV Circuit Breakers",
        "GIS"
      ],
      "companies": [
        "AEMO",
        "Transgrid",
        "Powerlink"
      ],
      "fundingSources": [
        "Australian Government",
        "State Governments"
      ],
      "projectValue": "AUD 3 billion+",
      "capacityMW": 0,
      "mpEngagementWindow": "Q4 2024 - Q4 2027",
      "mpServices": [
        "Factory Acceptance Testing",
        "QAQC Inspection",
        "Site Supervision",
        "Vendor Assessment"
      ],
      "priority": "High",
      "sourceUrl": "https://www.aemo.com.au/newsroom/media-release/vni-west-reaches-regulatory-investment-test-for-transmission-rit-t-final-report",
      "summary": "A critical new 500kV interconnector project designed to increase electricity transfer capability between Victoria and NSW. The project has reached its RIT-T Final Report stage, with detailed design and major HV equipment procurement tenders expected in late 2024."
    },
    {
      "projectName": "Western Downs Green Power Hub Expansion",
      "location": "Western Downs, Queensland",
      "country": "Australia",
      "procurementStart": "Q1 2024",
      "procurementStatus": "Planning",
      "assetTypes": [
        "Solar PV",
        "BESS",
        "Substation",
        "HV Transformers"
      ],
      "companies": [
        "Neoen"
      ],
      "fundingSources": [
        "Private Investment"
      ],
      "projectValue": "AUD 500 million",
      "capacityMW": 200,
      "mpEngagementWindow": "Q4 2024 - Q3 2026",
      "mpServices": [
        "Vendor Assessment",
        "Factory Acceptance Testing",
        "QAQC Inspection"
      ],
      "priority": "Medium",
      "sourceUrl": "https://reneweconomy.com.au/neoen-proposes-big-expansion-for-western-downs-solar-and-battery-hub/",
      "summary": "Proposed expansion of the operational Western Downs Green Power Hub to include additional solar PV and a significant BESS component. The project is in the approvals stage, with procurement for new solar modules, battery systems, and substation upgrades anticipated in 2025."
    },
    {
      "projectName": "Lot 1 (Leilão de Transmissão nº 02/2023)",
      "location": "Bahia, Minas Gerais, Espírito Santo",
      "country": "Brazil",
      "procurementStart": "Q2 2024",
      "procurementStatus": "Awarded",
      "assetTypes": [
        "HV Transmission",
        "Substation",
        "HV Transformers",
        "HV Circuit Breakers",
        "GIS"
      ],
      "companies": [
        "Consórcio Olympus XVI (Mercury II Transmissora de Energia Elétrica S.A.)"
      ],
      "fundingSources": [
        "BNDES",
        "Private Investment"
      ],
      "projectValue": "BRL 5.5 billion",
      "capacityMW": 0,
      "mpEngagementWindow": "Q3 2024 - Q4 2027",
      "mpServices": [
        "Factory Acceptance Testing",
        "QAQC Inspection",
        "Site Supervision",
        "Vendor Assessment"
      ],
      "priority": "High",
      "sourceUrl": "https://www.aneel.gov.br/sala-de-imprensa-exibicao?url=/web/guest/sala-de-imprensa-exibicao?url=/web/guest/noticias/-/asset_publisher/TqX4VzLgiuA8/content/aneel-promove-leilao-de-transmissao-com-r-18-2-bilhoes-em-investimentos-previstos/6568774?redirect=/",
      "summary": "Major transmission project connecting Bahia, Minas Gerais, and Espírito Santo, comprising approximately 1,500 km of new 500 kV and 230 kV lines and new/expanded substations. Concession awarded in Dec 2023, with detailed engineering and procurement for HV equipment ongoing or imminent."
    },
    {
      "projectName": "Lot 2 (Leilão de Transmissão nº 02/2023)",
      "location": "Bahia, Minas Gerais",
      "country": "Brazil",
      "procurementStart": "Q2 2024",
      "procurementStatus": "Awarded",
      "assetTypes": [
        "HV Transmission",
        "Substation",
        "HV Transformers",
        "HV Circuit Breakers"
      ],
      "companies": [
        "Consórcio Gênesis (EDP Transmissão SP-MG S.A.)"
      ],
      "fundingSources": [
        "BNDES",
        "Private Investment"
      ],
      "projectValue": "BRL 3.2 billion",
      "capacityMW": 0,
      "mpEngagementWindow": "Q3 2024 - Q4 2027",
      "mpServices": [
        "Factory Acceptance Testing",
        "QAQC Inspection",
        "Site Supervision",
        "Vendor Assessment"
      ],
      "priority": "High",
      "sourceUrl": "https://www.aneel.gov.br/sala-de-imprensa-exibicao?url=/web/guest/sala-de-imprensa-exibicao?url=/web/guest/noticias/-/asset_publisher/TqX4VzLgiuA8/content/aneel-promove-leilao-de-transmissao-com-r-18-2-bilhoes-em-investimentos-previstos/6568774?redirect=/",
      "summary": "Extensive transmission lines and substations across Bahia and Minas Gerais (approx. 1,000 km, 500 kV). Concession awarded in Dec 2023. Procurement for major HV components, including transformers and switchgear, will be a primary focus for the concessionaire over the next 12-24 months."
    },
    {
      "projectName": "Lot 3 (Leilão de Transmissão nº 02/2023)",
      "location": "Maranhão, Tocantins, Goiás, Minas Gerais",
      "country": "Brazil",
      "procurementStart": "Q2 2024",
      "procurementStatus": "Awarded",
      "assetTypes": [
        "HV Transmission",
        "Substation",
        "HV Transformers",
        "HV Circuit Breakers"
      ],
      "companies": [
        "Consórcio Paraná (Elecnor)"
      ],
      "fundingSources": [
        "BNDES",
        "Private Investment"
      ],
      "projectValue": "BRL 2.8 billion",
      "capacityMW": 0,
      "mpEngagementWindow": "Q3 2024 - Q4 2027",
      "mpServices": [
        "Factory Acceptance Testing",
        "QAQC Inspection",
        "Site Supervision",
        "Vendor Assessment"
      ],
      "priority": "High",
      "sourceUrl": "https://www.aneel.gov.br/sala-de-imprensa-exibicao?url=/web/guest/sala-de-imprensa-exibicao?url=/web/guest/noticias/-/asset_publisher/TqX4VzLgiuA8/content/aneel-promove-leilao-de-transmissao-com-r-18-2-bilhoes-em-investimentos-previstos/6568774?redirect=/",
      "summary": "Development of 1,000+ km of 500 kV and 230 kV transmission lines and associated substations connecting Maranhão, Tocantins, Goiás, and Minas Gerais. Concession awarded in Dec 2023. Major procurement for HV equipment and EPC services will be active from mid-2024."
    },
    {
      "projectName": "Serra da Palmeira Wind Farm Complex",
      "location": "Piauí",
      "country": "Brazil",
      "procurementStart": "Q4 2023",
      "procurementStatus": "Under Construction",
      "assetTypes": [
        "Wind",
        "Substation",
        "HV Transmission",
        "HV Transformers"
      ],
      "companies": [
        "ENGIE Brasil Energia"
      ],
      "fundingSources": [
        "BNDES",
        "Private Investment"
      ],
      "projectValue": "BRL 2.3 billion",
      "capacityMW": 343,
      "mpEngagementWindow": "Q3 2024 - Q2 2025",
      "mpServices": [
        "QAQC Inspection",
        "Factory Acceptance Testing",
        "Site Supervision"
      ],
      "priority": "High",
      "sourceUrl": "https://www.bndes.gov.br/wps/portal/site/home/imprensa/noticias/detalhes/noticia/20231128_engie",
      "summary": "A large wind farm complex being developed by ENGIE in Piauí. BNDES financing approved in late 2023. Construction is ongoing, and specialist procurement for additional wind turbine components, substation expansion, and grid connection elements requiring FAT and inspection is expected."
    },
    {
      "projectName": "Sol do Sertão IV Solar Complex",
      "location": "Bahia",
      "country": "Brazil",
      "procurementStart": "Q1 2024",
      "procurementStatus": "Planning",
      "assetTypes": [
        "Solar PV",
        "Substation",
        "HV Transmission",
        "HV Transformers"
      ],
      "companies": [
        "Essentia Energia"
      ],
      "fundingSources": [
        "Private Investment"
      ],
      "projectValue": "BRL 1.5 billion",
      "capacityMW": 500,
      "mpEngagementWindow": "Q4 2024 - Q4 2026",
      "mpServices": [
        "Vendor Assessment",
        "Factory Acceptance Testing",
        "QAQC Inspection"
      ],
      "priority": "Medium",
      "sourceUrl": "https://absolar.org.br/noticia/essentia-energia-avanca-com-projeto-solar-de-500-mw-na-bahia/",
      "summary": "Expansion of the Sol do Sertão solar complex in Bahia. The project is in the environmental licensing and pre-construction phase. Major procurement for solar panels, inverters, and significant grid connection infrastructure, including a new substation, is expected to begin in late 2024."
    },
    {
      "projectName": "Horizonte Solar (Solar Complex)",
      "location": "Piauí",
      "country": "Brazil",
      "procurementStart": "Q2 2024",
      "procurementStatus": "Planning",
      "assetTypes": [
        "Solar PV",
        "Substation",
        "HV Transmission",
        "HV Transformers"
      ],
      "companies": [
        "Voltalia"
      ],
      "fundingSources": [
        "Private Investment"
      ],
      "projectValue": "BRL 1 billion",
      "capacityMW": 320,
      "mpEngagementWindow": "Q1 2025 - Q3 2026",
      "mpServices": [
        "Vendor Assessment",
        "Factory Acceptance Testing",
        "QAQC Inspection",
        "Technical Due Diligence"
      ],
      "priority": "Medium",
      "sourceUrl": "https://www.pv-magazine-brasil.com/2024/01/15/voltalia-inicia-construcao-de-complexo-solar-no-piaui/",
      "summary": "A large-scale solar PV project in Piauí. While construction recently began for initial phases, procurement for subsequent stages, including grid connection works, substation components, and high-voltage equipment, is expected to continue into 2025."
    },
    {
      "projectName": "Fazenda Curral Queimado Wind Farm",
      "location": "Rio Grande do Norte",
      "country": "Brazil",
      "procurementStart": "Q3 2023",
      "procurementStatus": "Under Construction",
      "assetTypes": [
        "Wind",
        "Substation",
        "HV Transmission",
        "HV Transformers",
        "HV Circuit Breakers"
      ],
      "companies": [
        "Casa dos Ventos"
      ],
      "fundingSources": [
        "BNDES",
        "Private Investment"
      ],
      "projectValue": "BRL 1.8 billion",
      "capacityMW": 200,
      "mpEngagementWindow": "Q3 2024 - Q2 2025",
      "mpServices": [
        "QAQC Inspection",
        "Factory Acceptance Testing",
        "Site Supervision"
      ],
      "priority": "High",
      "sourceUrl": "https://www.abeeolica.org.br/noticias/casa-dos-ventos-avanca-em-projeto-eólico-no-rn/",
      "summary": "A 200 MW wind farm currently under construction. While turbine installation is ongoing, specialist procurement for final substation components, grid integration, and commissioning inspections for HV equipment remain active through 2024 and early 2025."
    },
    {
      "projectName": "Leilão de Transmissão nº 01/2024 (Future Projects)",
      "location": "Various States, Brazil",
      "country": "Brazil",
      "procurementStart": "Q3 2024",
      "procurementStatus": "Pre-tender",
      "assetTypes": [
        "HV Transmission",
        "Substation",
        "HV Transformers",
        "HV Circuit Breakers",
        "GIS"
      ],
      "companies": [],
      "fundingSources": [
        "BNDES",
        "Private Investment"
      ],
      "projectValue": "BRL 15 billion+",
      "capacityMW": 0,
      "mpEngagementWindow": "Q1 2025 - Q4 2028",
      "mpServices": [
        "Technical Due Diligence",
        "Vendor Assessment",
        "Factory Acceptance Testing",
        "QAQC Inspection",
        "Site Supervision"
      ],
      "priority": "High",
      "sourceUrl": "https://www.aneel.gov.br/agenda-de-eventos/-/asset_publisher/h4h03bB4W97L/content/aneel-divulga-agenda-de-leiloes-para-2024/6568774?redirect=/",
      "summary": "ANEEL has announced a new transmission auction for 2024, expected to award concessions for substantial new HV transmission lines and substations across Brazil. The details of the lots and their locations are being finalized, but procurement will be highly active in 2025-2026."
    },
    {
      "projectName": "Guanambi Solar Complex Expansion",
      "location": "Guanambi, Bahia",
      "country": "Brazil",
      "procurementStart": "Q4 2023",
      "procurementStatus": "Under Construction",
      "assetTypes": [
        "Solar PV",
        "Substation",
        "HV Transformers"
      ],
      "companies": [
        "Neoenergia"
      ],
      "fundingSources": [
        "Private Investment"
      ],
      "projectValue": "BRL 800 million",
      "capacityMW": 150,
      "mpEngagementWindow": "Q3 2024 - Q1 2025",
      "mpServices": [
        "QAQC Inspection",
        "Factory Acceptance Testing",
        "Site Supervision"
      ],
      "priority": "High",
      "sourceUrl": "https://www.neoenergia.com/pt-br/sala-de-imprensa/noticias/Paginas/Neoenergia-investe-na-expansao-de-usina-solar-na-Bahia.aspx",
      "summary": "Expansion of the Guanambi Solar Complex. Construction is progressing, with final electrical installations and grid connection components, including substation equipment, requiring ongoing QAQC and FAT prior to commissioning in late 2024/early 2025."
    },
    {
      "projectName": "Serra das Almas Wind Farm",
      "location": "Rio Grande do Norte",
      "country": "Brazil",
      "procurementStart": "Q1 2024",
      "procurementStatus": "Planning",
      "assetTypes": [
        "Wind",
        "Substation",
        "HV Transmission",
        "HV Transformers"
      ],
      "companies": [
        "Patria Investimentos"
      ],
      "fundingSources": [
        "Private Investment"
      ],
      "projectValue": "BRL 1.2 billion",
      "capacityMW": 250,
      "mpEngagementWindow": "Q4 2024 - Q3 2026",
      "mpServices": [
        "Vendor Assessment",
        "Factory Acceptance Testing",
        "QAQC Inspection"
      ],
      "priority": "Medium",
      "sourceUrl": "https://www.abeeolica.org.br/noticias/novos-projetos-de-energia-eolica-avancam-no-nordeste/",
      "summary": "A new large-scale wind farm project in Rio Grande do Norte. Currently in advanced planning and licensing phases, with major procurement for wind turbines, substation components, and grid connection infrastructure expected to commence by late 2024."
    }
  ],
  "lastScan": "today"
}